Workbook

Sheet 주차별 매출이익 보고서
B1: 주차별 매출이익 보고서-28차
B5: 경영지원부 강명훈 | C5: 46245 | M5: (단위:원)
B6: 품명 | C6: 매출액 | D6: 매출비율 | E6: 기초상품재고액 | F6: 기말상품재고액 | G6: 매입액(상품+포워딩) | H6: 그외통관비 | I6: 매출원가 | J6: 매출이익 | K6: 이익률 | L6: 불량금액 | M6: 불량율 | N6: 매출액 | O6: 그 외 매출액 | P6: 상품 금액(구매) | Q6: 구매금액 | R6: 환율 | S6: 포워딩비용(USD) | T6: 포워딩 원화환산 | U6: 상품구매비율
B7: 콜롬비아 수국 | C7: =N7+L7+O7 -> 56479424 | D7: =IFERROR((C7/$C$23),"") -> 0.23112494 | E7: 1793373.4 | F7: =(G7+H7)/SUMIF(구매현황!N:N,'주차별 매출이익 보고서'!B7,구매현황!D:D)*SUM(재고잔량!M7:M23) -> 3635624.8 | G7: =P7+T7 -> 50587531 | H7: =그외통관비!I35 -> 2242000 | I7: =E7+G7+H7-F7 -> 50987280 | J7: =C7-I7 -> 5492144 | K7: =IFERROR((J7/C7),"") -> 0.097241502 | L7: =SUMIF(불량차감!$J:$J,'주차별 매출이익 보고서'!B7,불량차감!$F:$F) -> -427272 | M7: =IFERROR(-(L7/C7),"") -> 0.0075650913 | N7: =SUMIF(판매현황!I:I,'주차별 매출이익 보고서'!B7,판매현황!E:E) -> 58939286 | O7: =SUMIF('그 외 매출액'!J:J,'주차별 매출이익 보고서'!B7,'그 외 매출액'!F:F) -> -2032590 | P7: =Q7*R7 -> 25267603 | Q7: =SUMIF(구매현황!N:N,'주차별 매출이익 보고서'!B7,구매현황!G:G) -> 16317.26 | R7: 1548.52 | S7: =SUMIF(포워딩!$N:$N,'주차별 매출이익 보고서'!B7,포워딩!$G:$G) -> 16351.05 | T7: =S7*R7 -> 25319928 | U7: =P7/$P$23 -> 0.17749632
B8: 콜롬비아 카네이션 | C8: =N8+L8+O8 -> 86982630 | D8: =IFERROR((C8/$C$23),"") -> 0.35595008 | E8: 1404898.6 | F8: =(G8+H8)/SUMIF(구매현황!N:N,'주차별 매출이익 보고서'!B8,구매현황!D:D)*SUM(재고잔량!M30:M32) -> 9409702.9 | G8: =P8+T8 -> 84059952 | H8: ='콜롬비아 1차'!H22+'콜롬비아 2차'!H22 -> 3483055 | I8: =E8+G8+H8-F8 -> 79538203 | J8: =C8-I8 -> 7444427.4 | K8: =IFERROR((J8/C8),"") -> 0.085585218 | L8: =SUMIF(불량차감!$J:$J,'주차별 매출이익 보고서'!B8,불량차감!$F:$F) -> -562545 | M8: =IFERROR(-(L8/C8),"") -> 0.0064673257 | N8: =SUMIF(판매현황!I:I,'주차별 매출이익 보고서'!B8,판매현황!E:E) -> 87739630 | O8: =SUMIF('그 외 매출액'!J:J,'주차별 매출이익 보고서'!B8,'그 외 매출액'!F:F) -> -194455 | P8: =Q8*R8 -> 56016162 | Q8: =SUMIF(구매현황!N:N,'주차별 매출이익 보고서'!B8,구매현황!G:G) -> 36174 | R8: 1548.52 | S8: ='콜롬비아 1차'!F22+'콜롬비아 2차'!F22 -> 18110.06 | T8: =S8*R8 -> 28043789 | U8: =P8/$P$23 -> 0.3934945
B9: 콜롬비아 장미 | C9: =N9+L9+O9 -> 32610458 | D9: =IFERROR((C9/$C$23),"") -> 0.13344843 | E9: 2010261.3 | F9: =(G9+H9)/SUMIF(구매현황!N:N,'주차별 매출이익 보고서'!B9,구매현황!D:D)*재고잔량!M92 -> 1598667.1 | G9: =P9+T9 -> 25463382 | H9: ='콜롬비아 1차'!H21+'콜롬비아 2차'!H21 -> 1065088.6 | I9: =E9+G9+H9-F9 -> 26940065 | J9: =C9-I9 -> 5670393.5 | K9: =IFERROR((J9/C9),"") -> 0.17388267 | L9: =SUMIF(불량차감!$J:$J,'주차별 매출이익 보고서'!B9,불량차감!$F:$F) -> -380091 | M9: =IFERROR(-(L9/C9),"") -> 0.011655494 | N9: =SUMIF(판매현황!I:I,'주차별 매출이익 보고서'!B9,판매현황!E:E) -> 33124094 | O9: =SUMIF('그 외 매출액'!J:J,'주차별 매출이익 보고서'!B9,'그 외 매출액'!F:F) -> -133545 | P9: =Q9*R9 -> 17035269 | Q9: =SUMIF(구매현황!N:N,'주차별 매출이익 보고서'!B9,구매현황!G:G) -> 11001 | R9: 1548.52 | S9: ='콜롬비아 1차'!F21+'콜롬비아 2차'!F21 -> 5442.6893 | T9: =S9*R9 -> 8428113.2 | U9: =P9/$P$23 -> 0.11966697
B10: 콜롬비아 루스커스 | C10: =N10+L10+O10 -> 10547993 | D10: =IFERROR((C10/$C$23),"") -> 0.043164468 | F10: =(G10+H10)/SUMIF(구매현황!N:N,'주차별 매출이익 보고서'!B10,구매현황!D:D)*재고잔량!M72 -> 578629.63 | G10: =P10+T10 -> 8854925.5 | H10: ='콜롬비아 1차'!H24+'콜롬비아 2차'!H24 -> 258491.18 | I10: =E10+G10+H10-F10 -> 8534787.1 | J10: =C10-I10 -> 2013205.9 | K10: =IFERROR((J10/C10),"") -> 0.19086152 | L10: =SUMIF(불량차감!$J:$J,'주차별 매출이익 보고서'!B10,불량차감!$F:$F) -> -21545 | M10: =IFERROR(-(L10/C10),"") -> 0.0020425687 | N10: =SUMIF(판매현황!I:I,'주차별 매출이익 보고서'!B10,판매현황!E:E) -> 10556811 | O10: =SUMIF('그 외 매출액'!J:J,'주차별 매출이익 보고서'!B10,'그 외 매출액'!F:F) -> 12727 | P10: =Q10*R10 -> 6726383.8 | Q10: =SUMIF(구매현황!N:N,'주차별 매출이익 보고서'!B10,구매현황!G:G) -> 4343.75 | R10: 1548.52 | S10: ='콜롬비아 1차'!F24+'콜롬비아 2차'!F24 -> 1374.5652 | T10: =S10*R10 -> 2128541.8 | U10: =P10/$P$23 -> 0.047250559
B11: 콜롬비아 알스트로 | C11: =N11+L11+O11 -> 3800488 | D11: =IFERROR((C11/$C$23),"") -> 0.015552347 | F11: =(G11+H11)/SUMIF(구매현황!N:N,'주차별 매출이익 보고서'!B11,구매현황!D:D)*SUM(재고잔량!M79:M85) -> 63272.881 | G11: =P11+T11 -> 3990405.8 | H11: ='콜롬비아 1차'!H23+'콜롬비아 2차'!H23 -> 243125.14 | I11: =E11+G11+H11-F11 -> 4170258.1 | J11: =C11-I11 -> -369770.09 | K11: =IFERROR((J11/C11),"") -> -0.097295423 | L11: =SUMIF(불량차감!$J:$J,'주차별 매출이익 보고서'!B11,불량차감!$F:$F) -> -44545 | M11: =IFERROR(-(L11/C11),"") -> 0.011720863 | N11: =SUMIF(판매현황!I:I,'주차별 매출이익 보고서'!B11,판매현황!E:E) -> 3865943 | O11: =SUMIF('그 외 매출액'!J:J,'주차별 매출이익 보고서'!B11,'그 외 매출액'!F:F) -> -20910 | P11: =Q11*R11 -> 2081210.9 | Q11: =SUMIF(구매현황!N:N,'주차별 매출이익 보고서'!B11,구매현황!G:G) -> 1344 | R11: 1548.52 | S11: ='콜롬비아 1차'!F23+'콜롬비아 2차'!F23 -> 1232.9159 | T11: =S11*R11 -> 1909194.9 | U11: =P11/$P$23 -> 0.014619799
B12: 네덜란드 | C12: =N12+L12+O12 -> 13263756 | D12: =IFERROR((C12/$C$23),"") -> 0.054277906 | E12: 177446.63 | F12: 206316.3 | G12: =P12+T12 -> 11289115 | H12: =그외통관비!I36 -> 610120 | I12: =E12+G12+H12-F12 -> 11870365 | J12: =C12-I12 -> 1393391.1 | K12: =IFERROR((J12/C12),"") -> 0.10505253 | L12: =SUMIF(불량차감!$J:$J,'주차별 매출이익 보고서'!B12,불량차감!$F:$F) -> -1005728 | M12: =IFERROR(-(L12/C12),"") -> 0.075825279 | N12: =SUMIF(판매현황!I:I,'주차별 매출이익 보고서'!B12,판매현황!E:E) -> 14572528 | O12: =SUMIF('그 외 매출액'!J:J,'주차별 매출이익 보고서'!B12,'그 외 매출액'!F:F) -> -303044 | P12: =Q12*R12 -> 8812227.7 | Q12: =SUMIF(구매현황!N:N,'주차별 매출이익 보고서'!B12,구매현황!G:G) -> 5065.11 | R12: 1739.79 | S12: =SUMIF(포워딩!$N:$N,'주차별 매출이익 보고서'!B12,포워딩!$G:$G) -> 1423.67 | T12: =S12*R12 -> 2476886.8 | U12: =P12/$P$23 -> 0.061902904
B13: 호주 | C13: =N13+L13+O13 -> 3690273 | D13: =IFERROR((C13/$C$23),"") -> 0.015101325 | E13: 7843425.4 | F13: 5322349.2 | G13: =P13+T13 -> 0 | H13: =그외통관비!I38 -> 0 | I13: =E13+G13+H13-F13 -> 2521076.2 | J13: =C13-I13 -> 1169196.8 | K13: =IFERROR((J13/C13),"") -> 0.31683206 | L13: =SUMIF(불량차감!$J:$J,'주차별 매출이익 보고서'!B13,불량차감!$F:$F) -> 0 | M13: =IFERROR(-(L13/C13),"") -> 0 | N13: =SUMIF(판매현황!I:I,'주차별 매출이익 보고서'!B13,판매현황!E:E) -> 3690273 | O13: =SUMIF('그 외 매출액'!J:J,'주차별 매출이익 보고서'!B13,'그 외 매출액'!F:F) -> 0 | P13: =Q13*R13 -> 0 | Q13: =SUMIF(구매현황!N:N,'주차별 매출이익 보고서'!B13,구매현황!G:G) -> 0 | T13: =S13*R13 -> 0 | U13: =P13/$P$23 -> 0
B14: 태국 | C14: =N14+L14+O14 -> 2996547 | D14: =IFERROR((C14/$C$23),"") -> 0.012262461 | G14: =P14+T14 -> 3190014.2 | H14: =그외통관비!I37 -> 285520 | I14: =E14+G14+H14-F14 -> 3475534.2 | J14: =C14-I14 -> -478987.21 | K14: =IFERROR((J14/C14),"") -> -0.15984638 | L14: =SUMIF(불량차감!$J:$J,'주차별 매출이익 보고서'!B14,불량차감!$F:$F) -> -106364 | M14: =IFERROR(-(L14/C14),"") -> 0.035495522 | N14: =SUMIF(판매현황!I:I,'주차별 매출이익 보고서'!B14,판매현황!E:E) -> 3122729 | O14: =SUMIF('그 외 매출액'!J:J,'주차별 매출이익 보고서'!B14,'그 외 매출액'!F:F) -> -19818 | P14: =Q14*R14 -> 2199773.6 | Q14: =SUMIF(구매현황!N:N,'주차별 매출이익 보고서'!B14,구매현황!G:G) -> 1444.9 | R14: 1522.44 | S14: =SUMIF(포워딩!$N:$N,'주차별 매출이익 보고서'!B14,포워딩!$G:$G) -> 650.43 | T14: =S14*R14 -> 990240.65 | U14: =P14/$P$23 -> 0.015452661
B15: 중국 | C15: =N15+L15+O15 -> 7772472 | D15: =IFERROR((C15/$C$23),"") -> 0.031806489 | F15: 242459.2 | G15: =P15+T15 -> 5224438.1 | H15: =그외통관비!I40 -> 1465640 | I15: =E15+G15+H15-F15 -> 6447618.9 | J15: =C15-I15 -> 1324853.1 | K15: =IFERROR((J15/C15),"") -> 0.17045453 | L15: =SUMIF(불량차감!$J:$J,'주차별 매출이익 보고서'!B15,불량차감!$F:$F) -> -1639999 | M15: =IFERROR(-(L15/C15),"") -> 0.21100095 | N15: =SUMIF(판매현황!I:I,'주차별 매출이익 보고서'!B15,판매현황!E:E) -> 10089562 | O15: =SUMIF('그 외 매출액'!J:J,'주차별 매출이익 보고서'!B15,'그 외 매출액'!F:F) -> -677091 | P15: =Q15*R15 -> 3614426.4 | Q15: =SUMIF(구매현황!N:N,'주차별 매출이익 보고서'!B15,구매현황!G:G) -> 16120 | R15: 224.22 | S15: =SUMIF(포워딩!$N:$N,'주차별 매출이익 보고서'!B15,포워딩!$G:$G) -> 7180.5 | T15: =S15*R15 -> 1610011.7 | U15: =P15/$P$23 -> 0.025390117
B16: 에콰도르 | C16: =N16+L16+O16 -> 2610910 | D16: =IFERROR((C16/$C$23),"") -> 0.010684359 | G16: =P16+T16 -> 2031620.1 | H16: =그외통관비!I41 -> 618740 | I16: =E16+G16+H16-F16 -> 2650360.1 | J16: =C16-I16 -> -39450.058 | K16: =IFERROR((J16/C16),"") -> -0.015109697 | L16: =SUMIF(불량차감!$J:$J,'주차별 매출이익 보고서'!B16,불량차감!$F:$F) -> 0 | M16: =IFERROR(-(L16/C16),"") -> 0 | N16: =SUMIF(판매현황!I:I,'주차별 매출이익 보고서'!B16,판매현황!E:E) -> 2654546 | O16: =SUMIF('그 외 매출액'!J:J,'주차별 매출이익 보고서'!B16,'그 외 매출액'!F:F) -> -43636 | P16: =Q16*R16 -> 1202727.6 | Q16: =SUMIF(구매현황!N:N,'주차별 매출이익 보고서'!B16,구매현황!G:G) -> 790 | R16: 1522.44 | S16: =SUMIF(포워딩!$N:$N,'주차별 매출이익 보고서'!B16,포워딩!$G:$G) -> 544.45 | T16: =S16*R16 -> 828892.46 | U16: =P16/$P$23 -> 0.0084487525
B17: 미국 | C17: =N17+L17+O17 -> 0 | D17: =IFERROR((C17/$C$23),"") -> 0 | G17: =P17+T17 -> 0 | H17: =그외통관비!I39 -> 0 | I17: =E17+G17+H17-F17 -> 0 | J17: =C17-I17 -> 0 | K17: =IFERROR((J17/C17),"") | L17: =SUMIF(불량차감!$J:$J,'주차별 매출이익 보고서'!B17,불량차감!$F:$F) -> 0 | M17: =IFERROR(-(L17/C17),"") | N17: =SUMIF(판매현황!I:I,'주차별 매출이익 보고서'!B17,판매현황!E:E) -> 0 | O17: =SUMIF('그 외 매출액'!J:J,'주차별 매출이익 보고서'!B17,'그 외 매출액'!F:F) -> 0 | P17: =Q17*R17 -> 0 | Q17: =SUMIF(구매현황!N:N,'주차별 매출이익 보고서'!B17,구매현황!G:G) -> 0 | T17: =S17*R17 -> 0 | U17: =P17/$P$23 -> 0
B18: 이스라엘 | C18: =N18+L18+O18 -> 0 | D18: =IFERROR((C18/$C$23),"") -> 0 | G18: =P18+T18 -> 0 | H18: =그외통관비!I42 -> 0 | I18: =E18+G18+H18 -> 0 | J18: =C18-I18+F18 -> 0 | K18: =IFERROR((J18/(C18+F18)),"") | L18: =SUMIF(불량차감!$J:$J,'주차별 매출이익 보고서'!B18,불량차감!$F:$F) -> 0 | M18: =IFERROR(-(L18/C18),"") | N18: =SUMIF(판매현황!I:I,'주차별 매출이익 보고서'!B18,판매현황!E:E) -> 0 | O18: =SUMIF('그 외 매출액'!J:J,'주차별 매출이익 보고서'!B18,'그 외 매출액'!F:F) -> 0 | P18: =Q18*R18 -> 0 | Q18: =SUMIF(구매현황!N:N,'주차별 매출이익 보고서'!B18,구매현황!G:G) -> 0 | S18: =SUMIF(포워딩!$N:$N,'주차별 매출이익 보고서'!B18,포워딩!$G:$G) -> 0 | T18: =S18*R18 -> 0 | U18: =P18/$P$23 -> 0
B19: 뉴질랜드 | C19: =N19+L19+O19 -> 0 | D19: =IFERROR((C19/$C$23),"") -> 0 | G19: =P19+T19 -> 0 | H19: =그외통관비!I43 -> 0 | I19: =E19+G19+H19 -> 0 | J19: =C19-I19+F19 -> 0 | K19: =IFERROR((J19/(C19+F19)),"") | L19: =SUMIF(불량차감!$J:$J,'주차별 매출이익 보고서'!B19,불량차감!$F:$F) -> 0 | M19: =IFERROR(-(L19/C19),"") | N19: =SUMIF(판매현황!I:I,'주차별 매출이익 보고서'!B19,판매현황!E:E) -> 0 | O19: =SUMIF('그 외 매출액'!J:J,'주차별 매출이익 보고서'!B19,'그 외 매출액'!F:F) -> 0 | P19: =Q19*R19 -> 0 | Q19: =SUMIF(구매현황!N:N,'주차별 매출이익 보고서'!B19,구매현황!G:G) -> 0 | S19: =SUMIF(포워딩!$N:$N,'주차별 매출이익 보고서'!B19,포워딩!$G:$G) -> 0 | T19: =S19*R19 -> 0 | U19: =P19/$P$23 -> 0
B20: 일본 | C20: =N20+L20+O20 -> 0 | D20: =IFERROR((C20/$C$23),"") -> 0 | G20: =P20+T20 -> 0 | H20: =그외통관비!I44 -> 0 | I20: =E20+G20+H20 -> 0 | J20: =C20-I20+F20 -> 0 | K20: =IFERROR((J20/(C20+F20)),"") | L20: =SUMIF(불량차감!$J:$J,'주차별 매출이익 보고서'!B20,불량차감!$F:$F) -> 0 | M20: =IFERROR(-(L20/C20),"") | N20: =SUMIF(판매현황!I:I,'주차별 매출이익 보고서'!B20,판매현황!E:E) -> 0 | O20: =SUMIF('그 외 매출액'!J:J,'주차별 매출이익 보고서'!B20,'그 외 매출액'!F:F) -> 0 | P20: =Q20*R20 -> 0 | Q20: =SUMIF(구매현황!N:N,'주차별 매출이익 보고서'!B20,구매현황!G:G) -> 0 | S20: =SUMIF(포워딩!$N:$N,'주차별 매출이익 보고서'!B20,포워딩!$G:$G) -> 0 | T20: =S20*R20 -> 0 | U20: =P20/$P$23 -> 0
B21: 베트남 | C21: =N21+L21+O21 -> 22993000 | D21: =IFERROR((C21/$C$23),"") -> 0.094091891 | F21: =(G21+H21)/SUMIF(구매현황!N:N,'주차별 매출이익 보고서'!B21,구매현황!D:D)*SUM(재고잔량!M152:M155) -> 909607.47 | G21: =P21+T21 -> 19399859 | H21: =그외통관비!I45 -> 1188330 | I21: =E21+G21+H21-F21 -> 19678581 | J21: =C21-I21 -> 3314418.9 | K21: =IFERROR((J21/C21),"") -> 0.14414904 | L21: =SUMIF(불량차감!$J:$J,'주차별 매출이익 보고서'!B21,불량차감!$F:$F) -> 0 | M21: =IFERROR(-(L21/C21),"") -> 0 | N21: =SUMIF(판매현황!I:I,'주차별 매출이익 보고서'!B21,판매현황!E:E) -> 23088000 | O21: =SUMIF('그 외 매출액'!J:J,'주차별 매출이익 보고서'!B21,'그 외 매출액'!F:F) -> -95000 | P21: =Q21*R21 -> 19399859 | Q21: =SUMIF(구매현황!N:N,'주차별 매출이익 보고서'!B21,구매현황!G:G) -> 12528 | R21: 1548.52 | T21: =S21*R21 -> 0 | U21: =P21/$P$23 -> 0.13627741
B22: 국내 | C22: =N22+L22+O22 -> 619546 | D22: =IFERROR((C22/$C$23),"") -> 0.0025353044 | H22: 0 | I22: =E22+G22+H22-F22 -> 0 | J22: =C22-I22 -> 619546 | K22: =IFERROR((J22/C22),"") -> 1 | L22: =SUMIF(불량차감!$J:$J,'주차별 매출이익 보고서'!B22,불량차감!$F:$F) -> 0 | M22: =IFERROR(-(L22/C22),"") -> 0 | N22: =SUMIF(판매현황!I:I,'주차별 매출이익 보고서'!B22,판매현황!E:E) -> 0 | O22: =SUMIF('그 외 매출액'!J:J,'주차별 매출이익 보고서'!B22,'그 외 매출액'!F:F) -> 619546
C23: =SUM(C7:C22) -> 244367497 | D23: =SUM(D7:D22) -> 1 | E23: =SUM(E7:E22) -> 13229405 | F23: =SUM(F7:F22) -> 21966629 | G23: =SUM(G7:G21) -> 2.1409124e+08 | H23: =SUM(H7:H21) -> 11460110 | I23: =SUM(I7:I21) -> 2.1681413e+08 | J23: =SUM(J7:J22) -> 27553369 | K23: =IFERROR((J23/(C23+F23)),"") -> 0.10345415 | L23: =SUM(L7:L21) -> -4188089 | M23: =IFERROR(-(L23/C23),"") -> 0.017138486 | N23: =SUM(N7:N21) -> 251443402 | O23: =SUM(O7:O21) -> -3507362 | P23: =SUM(P7:P21) -> 1.4235564e+08 | Q23: =SUM(Q7:Q21) -> 105128.02 | S23: =SUM(S7:S21) -> 52310.33 | T23: =SUM(T7:T21) -> 71735599 | U23: =SUM(U7:U20) -> 0.86372259
B25: 비고사항

Sheet 재고잔량
B1: 기초재고 | G1: 총합계 | J1: 기말재고 | O1: 총합계
G2: =G24+G33+G54+G67+G73+G86+G93++G105+G117+G134+G143+G149+G156 -> 20826000 | O2: =O24+O33+O54+O67+O73+O86+O93+O105+O117+O134+O143+O149+O156 -> 120238500
G3: =G2/1.1 -> 18932727 | O3: =O2/1.1 -> 1.0930773e+08
B5: 수국 | J5: 수국
B6: 품목 | C6: 박스 | D6: 박스당수량 | E6: 송이 | F6: 가격 | G6: 총계 | J6: 품목 | K6: 박스 | L6: 박스당수량 | M6: 송이 | N6: 가격 | O6: 총계
B7: 화이트 | C7: 6 | D7: 30 | E7: =C7*D7 -> 180 | F7: 2600 | G7: =E7*F7 -> 468000 | J7: 화이트 | K7: 5 | L7: 30 | M7: =K7*L7 -> 150 | N7: 2600 | O7: =M7*N7 -> 390000
B8: 블루 | D8: 30 | E8: =C8*D8 -> 0 | F8: 2700 | G8: =E8*F8 -> 0 | J8: 블루 | K8: 4 | L8: 30 | M8: =K8*L8 -> 120 | N8: 2700 | O8: =M8*N8 -> 324000
B9: 연그린 | C9: 1 | D9: 30 | E9: =C9*D9 -> 30 | F9: 3100 | G9: =E9*F9 -> 93000 | J9: 연그린 | L9: 30 | M9: =K9*L9 -> 0 | N9: 3100 | O9: =M9*N9 -> 0
B10: 진그린 | D10: 30 | E10: =C10*D10 -> 0 | F10: 3100 | G10: =E10*F10 -> 0 | J10: 진그린 | K10: 3 | L10: 30 | M10: =K10*L10 -> 90 | N10: 3100 | O10: =M10*N10 -> 279000
B11: S.PK | D11: 30 | E11: =C11*D11 -> 0 | F11: 3200 | G11: =E11*F11 -> 0 | H11: 스페셜핑크 | J11: S.PK | L11: 30 | M11: =K11*L11 -> 0 | N11: 3300 | O11: =M11*N11 -> 0 | P11: 스페셜핑크
B12: P.PK(BA) | C12: 8 | D12: 30 | E12: =C12*D12 -> 240 | F12: 3300 | G12: =E12*F12 -> 792000 | H12: 연핑크 | J12: P.PK(BA) | K12: 20 | L12: 30 | M12: =K12*L12 -> 600 | N12: 3300 | O12: =M12*N12 -> 1980000 | P12: 연핑크
B13: Abaricoque | D13: 30 | E13: =C13*D13 -> 0 | F13: 3300 | G13: =E13*F13 -> 0 | J13: Abaricoque | L13: 30 | M13: =K13*L13 -> 0 | N13: 3300 | O13: =M13*N13 -> 0
B14: 라벤다 | C14: 1 | D14: 30 | E14: =C14*D14 -> 30 | F14: 3300 | G14: =E14*F14 -> 99000 | J14: 라벤다 | K14: 8 | L14: 30 | M14: =K14*L14 -> 240 | N14: 3300 | O14: =M14*N14 -> 792000
B15: 다크핑크(Dark pink) | D15: 30 | E15: =C15*D15 -> 0 | F15: 3300 | G15: =E15*F15 -> 0 | J15: 다크핑크(Dark pink) | K15: 1 | L15: 30 | M15: =K15*L15 -> 30 | N15: 3300 | O15: =M15*N15 -> 99000
B16: 피치 | C16: 10 | D16: 30 | E16: =C16*D16 -> 300 | F16: 3300 | G16: =E16*F16 -> 990000 | J16: 피치 | K16: 16 | L16: 30 | M16: =K16*L16 -> 480 | N16: 3300 | O16: =M16*N16 -> 1584000
B17: 로즈우드 | D17: 30 | E17: =C17*D17 -> 0 | F17: 3300 | G17: =E17*F17 -> 0 | J17: 로즈우드 | L17: 30 | M17: =K17*L17 -> 0 | N17: 3300 | O17: =M17*N17 -> 0
B18: 골드피치 | D18: 30 | E18: =C18*D18 -> 0 | F18: 3200 | G18: =E18*F18 -> 0 | J18: 골드피치 | L18: 30 | M18: =K18*L18 -> 0 | N18: 3200 | O18: =M18*N18 -> 0
B19: 신라 누락 건 | J19: 신라 누락 건
B20: 진라벤더 | D20: 30 | E20: =C20*D20 -> 0 | F20: 3200 | G20: =E20*F20 -> 0 | H20: =SUM(E7:E23) -> 870 | I20: =SUM(M7:M23) -> 1770 | J20: 진라벤더 | L20: 30 | M20: =K20*L20 -> 0 | N20: 3300 | O20: =M20*N20 -> 0
B21: 모히또 | D21: 30 | E21: =C21*D21 -> 0 | F21: 2250 | G21: =E21*F21 -> 0 | H21: 20670 | I21: 21750 | J21: 모히또 | L21: 30 | M21: =K21*L21 -> 0 | N21: 2250 | O21: =M21*N21 -> 0
B22: 노랑 | C22: 3 | D22: 30 | E22: =C22*D22 -> 90 | F22: 3200 | G22: =E22*F22 -> 288000 | H22: =SUM(H20:H21) -> 21540 | I22: =SUM(I20:I21) -> 23520 | J22: 노랑 | L22: 30 | M22: =K22*L22 -> 0 | N22: 3200 | O22: =M22*N22 -> 0
B23: 연연핑크 | D23: 30 | E23: =C23*D23 -> 0 | F23: 3300 | G23: =E23*F23 -> 0 | J23: 연연핑크 | K23: 2 | L23: 30 | M23: =K23*L23 -> 60 | N23: 3300 | O23: =M23*N23 -> 198000
B24: 총계 | C24: =SUM(C7:C23) -> 29 | G24: =SUM(G7:G23) -> 2730000 | H24: =H22-I22 -> -1980 | J24: 총계 | K24: =SUM(K7:K23) -> 59 | O24: =SUM(O7:O23) -> 5646000
G25: =G24/1.1 -> 2481818.2 | O25: =O24/1.1 -> 5132727.3
B28: 카네이션 | J28: 카네이션
B29: 품목 | C29: 박스 | D29: 박스당수량 | E29: 단 | F29: 가격 | G29: 총계 | J29: 품목 | K29: 박스 | L29: 박스당수량 | M29: 단 | N29: 가격 | O29: 총계
B30: 카네이션 | C30: 10 | D30: 15 | E30: =C30*D30 -> 150 | F30: 11000 | G30: =E30*F30 -> 1650000 | J30: 카네이션 | K30: 65 | L30: 15 | M30: =K30*L30 -> 975 | N30: 110000 | O30: =M30*N30 -> 107250000
B31: 미니카네이션 | D31: 30 | E31: =C31*D31 -> 0 | F31: 7250 | G31: =E31*F31 -> 0 | H31: =SUM(E30:E32) -> 150 | I31: =SUM(M30:M32) -> 1005 | J31: 미니카네이션 | K31: 1 | L31: 30 | M31: =K31*L31 -> 30 | N31: 7250 | O31: =M31*N31 -> 217500
B32: 염색카네이션 | D32: 30 | E32: =C32*D32 -> 0 | F32: 16500 | G32: =E32*F32 -> 0 | H32: 7440 | I32: 7365 | J32: 염색카네이션 | L32: 30 | M32: =K32*L32 -> 0 | N32: 16500 | O32: =M32*N32 -> 0
B33: 총합계 | C33: =SUM(C30:C32) -> 10 | G33: =SUM(G30:G32) -> 1650000 | H33: =H31+H32 -> 7590 | I33: =I31+I32 -> 8370 | J33: 총합계 | K33: =SUM(K30:K32) -> 66 | O33: =SUM(O30:O32) -> 107467500
G34: =G33/1.1 -> 1500000 | O34: =O33/1.1 -> 97697727
H35: =H33-I33 -> -780
B37: 호주 | J37: 호주 | O37: 1068.23
B38: 품목 | E38: 단 | F38: 가격 | G38: 총계 | J38: 품목 | M38: 단 | N38: 가격 | O38: 총계
B39: 씨스타펀 | E39: 50 | F39: 9200 | G39: =E39*F39 -> 460000 | J39: 씨스타펀 | M39: 50 | N39: 9200 | O39: =M39*N39 -> 460000 | P39: 6.65 | Q39: =M39*P39 -> 332.5 | R39: =Q39*$O$37 -> 355186.48
B40: 엄브렐러펀 | E40: 141 | F40: 9700 | G40: =E40*F40 -> 1367700 | J40: 엄브렐러펀 | M40: 82 | N40: 9700 | O40: =M40*N40 -> 795400 | P40: 6.95 | Q40: =M40*P40 -> 569.9 | R40: =Q40*$O$37 -> 608784.28
B41: 스틸그라스 | E41: 120 | F41: 4900 | G41: =E41*F41 -> 588000 | J41: 스틸그라스 | M41: 120 | N41: 4900 | O41: =M41*N41 -> 588000 | P41: 3.5 | Q41: =M41*P41 -> 420 | R41: =Q41*$O$37 -> 448656.6
B42: 스테노카르푸스 | E42: 80 | F42: 15500 | G42: =E42*F42 -> 1240000 | J42: 스테노카르푸스 | M42: 30 | N42: 15500 | O42: =M42*N42 -> 465000 | P42: 11.25 | Q42: =M42*P42 -> 337.5 | R42: =Q42*$O$37 -> 360527.62
B43: 반커부쉬 | E43: 240 | F43: 18500 | G43: =E43*F43 -> 4440000 | J43: 반커부쉬 | M43: 105 | N43: 18500 | O43: =M43*N43 -> 1942500 | P43: 14.5 | Q43: =M43*P43 -> 1522.5 | R43: =Q43*$O$37 -> 1626380.2
B44: 에뮤페더 | E44: 100 | F44: 4500 | G44: =E44*F44 -> 450000 | J44: 에뮤페더 | M44: 100 | N44: 4500 | O44: =M44*N44 -> 450000 | P44: 4.05 | Q44: =M44*P44 -> 405 | R44: =Q44*$O$37 -> 432633.15
B45: 에뮤그라스 | F45: 6700 | G45: =E45*F45 -> 0 | J45: 에뮤그라스 | N45: 6700 | O45: =M45*N45 -> 0 | P45: 4.8 | Q45: =M45*P45 -> 0 | R45: =Q45*$O$37 -> 0
B46: 구아나클라우 | F46: 5500 | G46: =E46*F46 -> 0 | J46: 구아나클라우 | N46: 5500 | O46: =M46*N46 -> 0 | P46: 3.65 | Q46: =M46*P46 -> 0 | R46: =Q46*$O$37 -> 0
B47: 딩고펀 | F47: 5500 | G47: =E47*F47 -> 0 | J47: 딩고펀 | N47: 5500 | O47: =M47*N47 -> 0 | Q47: =M47*P47 -> 0 | R47: =Q47*$O$37 -> 0
B48: 코알라펀 | F48: 6600 | G48: =E48*F48 -> 0 | J48: 코알라펀 | N48: 6600 | O48: =M48*N48 -> 0 | P48: 4.8 | Q48: =M48*P48 -> 0 | R48: =Q48*$O$37 -> 0
B49: copper glow | F49: 13000 | G49: =E49*F49 -> 0 | H49: =SUM(E39:E52) -> 821 | I49: =SUM(M39:M52) -> 577 | J49: copper glow | N49: 13000 | O49: =M49*N49 -> 0 | P49: 8.5 | Q49: =M49*P49 -> 0 | R49: =Q49*$O$37 -> 0
B50: woolly bush | E50: 30 | F50: 13000 | G50: =E50*F50 -> 390000 | I50: 804 | J50: woolly bush | M50: 30 | N50: 13000 | O50: =M50*N50 -> 390000 | P50: 8.5 | Q50: =M50*P50 -> 255 | R50: =Q50*$O$37 -> 272398.65
B51: 레인보우 | F51: 8500 | G51: =E51*F51 -> 0 | H51: =SUM(H49:H50) -> 821 | I51: =SUM(I49:I50) -> 1381 | J51: 레인보우 | N51: 8500 | O51: =M51*N51 -> 0 | P51: 5.65 | Q51: =M51*P51 -> 0 | R51: =Q51*$O$37 -> 0
B52: Thryptomene Calycina Natural White | E52: 60 | J52: Thryptomene Calycina Natural White | M52: 60 | P52: 9.5 | Q52: =M52*P52 -> 570 | R52: =Q52*$O$37 -> 608891.1
B53: Thryptomene Calycina Natural pink | E53: 60 | J53: Thryptomene Calycina Natural pink | M53: 60 | P53: 9.5 | Q53: =M53*P53 -> 570 | R53: =Q53*$O$37 -> 608891.1
B54: 총계 | G54: =SUM(G39:G50) -> 8935700 | H54: =H51-I51 -> -560 | J54: 총계 | O54: =SUM(O39:O50) -> 5090900 | P54: =608410/2030 -> 299.70936 | Q54: =P54*SUM(M39:M53) -> 190914.86 | R54: =SUM(R39:R53) -> 5322349.2
G55: =G54/1.1 -> 8123363.6
B58: 미국 | J58: 미국
B59: 품목 | C59: 박스 | D59: 박스당수량 | E59: 단 | F59: 가격 | G59: 총계 | J59: 품목 | K59: 박스 | L59: 박스당수량 | M59: 단 | N59: 가격 | O59: 총계
B60: 레몬잎 | D60: 25 | E60: =C60*D60 -> 0 | F60: 5500 | G60: =E60*F60 -> 0 | J60: 레몬잎 | L60: 25 | M60: =K60*L60 -> 0 | N60: 5500 | O60: =M60*N60 -> 0 | P60: 4134.99
B61: 더글라스 | D61: 20 | E61: =C61*D61 -> 0 | F61: 6000 | G61: =E61*F61 -> 0 | J61: 더글라스 | L61: 20 | M61: =K61*L61 -> 0 | N61: 6000 | O61: =M61*N61 -> 0
E62: =C62*D62 -> 0 | F62: 5500 | G62: =E62*F62 -> 0 | M62: =K62*L62 -> 0 | N62: 6000 | O62: =M62*N62 -> 0
E63: =C63*D63 -> 0 | F63: 5500 | G63: =E63*F63 -> 0 | M63: =K63*L63 -> 0 | N63: 5500 | O63: =M63*N63 -> 0
E64: =C64*D64 -> 0 | F64: 5500 | G64: =E64*F64 -> 0 | M64: =K64*L64 -> 0 | N64: 5500 | O64: =M64*N64 -> 0
E65: =C65*D65 -> 0 | F65: 5500 | G65: =E65*F65 -> 0 | M65: =K65*L65 -> 0 | N65: 5500 | O65: =M65*N65 -> 0
E66: =C66*D66 -> 0 | F66: 5500 | G66: =E66*F66 -> 0 | M66: =K66*L66 -> 0 | N66: 5500 | O66: =M66*N66 -> 0
B67: 총계 | G67: =SUM(G60:G66) -> 0 | J67: 총계 | O67: =SUM(O60:O66) -> 0
G68: =G67/1.1 -> 0 | O68: =O67/1.1 -> 0
B71: 콜롬비아 루스커스 | J71: 콜롬비아 루스커스
B72: 루스커스 | D72: 25 | E72: =C72*D72 -> 0 | F72: 7900 | G72: =E72*F72 -> 0 | H72: =E72 -> 0 | I72: =M72 -> 100 | J72: 루스커스 | K72: 4 | L72: 25 | M72: =K72*L72 -> 100 | N72: 7900 | O72: =M72*N72 -> 790000
B73: 총계 | G73: =SUM(G72) -> 0 | H73: 1625 | I73: 1500 | J73: 총계 | O73: =SUM(O72) -> 790000
G74: =G73/1.1 -> 0 | H74: =SUM(H72:H73) -> 1625 | I74: =SUM(I72:I73) -> 1600 | O74: =O73/1.1 -> 718181.82
B77: 알스트로 | J77: 알스트로
B78: 품목 | C78: 박스 | D78: 박스당수량 | E78: 스팀 | F78: 가격 | G78: 총계 | J78: 품목 | K78: 박스 | L78: 박스당수량 | M78: 스팀 | N78: 가격 | O78: 총계
B79: 휘슬러 | D79: 160 | E79: =C79*D79 -> 0 | F79: 650 | G79: =E79*F79 -> 0 | J79: 휘슬러 | L79: 160 | M79: =K79*L79 -> 0 | N79: 650 | O79: =M79*N79 -> 0
B80: 두바이 | D80: 160 | E80: =C80*D80 -> 0 | F80: 650 | G80: =E80*F80 -> 0 | J80: 두바이 | L80: 160 | M80: =K80*L80 -> 0 | N80: 650 | O80: =M80*N80 -> 0
B81: 피피버터플러스 | D81: 160 | E81: =C81*D81 -> 0 | F81: 650 | G81: =E81*F81 -> 0 | J81: 피피버터플러스 | L81: 160 | M81: =K81*L81 -> 0 | N81: 650 | O81: =M81*N81 -> 0
B82: 골디 | D82: 160 | E82: =C82*D82 -> 0 | F82: 650 | G82: =E82*F82 -> 0 | J82: 골디 | L82: 160 | M82: =K82*L82 -> 0 | N82: 650 | O82: =M82*N82 -> 0
B83: 레드퀸 | D83: 160 | E83: =C83*D83 -> 0 | F83: 650 | G83: =E83*F83 -> 0 | J83: 레드퀸 | L83: 160 | M83: 110 | N83: 650 | O83: =M83*N83 -> 71500
B84: 노라 | D84: 160 | E84: =C84*D84 -> 0 | F84: 650 | G84: =E84*F84 -> 0 | J84: 피치 | L84: 160 | M84: =K84*L84 -> 0 | N84: 650 | O84: =M84*N84 -> 0
B85: 라벤더 | D85: 160 | E85: =C85*D85 -> 0 | F85: 650 | G85: =E85*F85 -> 0 | J85: 라벤더 | L85: 160 | M85: =K85*L85 -> 0 | N85: 650 | O85: =M85*N85 -> 0
B86: 총계 | G86: =SUM(G79:G85) -> 0 | J86: 총계 | O86: =SUM(O79:O85) -> 71500
G87: =G86/1.1 -> 0 | O87: =O86/1.1 -> 65000
B90: 콜롬비아 장미 | J90: 콜롬비아 장미
B91: 품목(50cm) | E91: 단 | F91: 가격 | G91: 총계 | J91: 품목(50cm) | M91: 단 | N91: 가격 | O91: 총계
B92: Be sweet | E92: 205 | F92: 12500 | G92: =E92*F92 -> 2562500 | M92: 170 | O92: =M92*N92 -> 0
B93: 총계 | G93: =SUM(G92:G92) -> 2562500 | J93: 총계 | O93: =SUM(O92:O92) -> 0
G94: =G93/1.1 -> 2329545.5 | O94: =O93/1.1 -> 0
B96: 이스라엘 | J96: 이스라엘
B97: 품목 | C97: 박스 | D97: 박스당수량 | E97: 스팀 | F97: 가격 | G97: 총계 | J97: 품목 | K97: 박스 | L97: 박스당수량 | M97: 스팀 | N97: 가격 | O97: 총계
B98: Hirsutum White (10F) | D98: 45 | E98: =C98*D98 -> 0 | F98: 5600 | G98: =E98*F98 -> 0 | J98: Hirsutum White (10F) | L98: 45 | M98: =K98*L98 -> 0 | N98: 5600 | O98: =M98*N98 -> 0
B99: Hirsutum White (8F) | D99: 55 | E99: =C99*D99 -> 0 | F99: 5200 | G99: =E99*F99 -> 0 | J99: Hirsutum White (8F) | L99: 55 | M99: =K99*L99 -> 0 | N99: 5200 | O99: =M99*N99 -> 0
B100: 그레빌레아 70cm | D100: 100 | E100: =C100*D100 -> 0 | F100: 2100 | G100: =E100*F100 -> 0 | J100: 그레빌레아 70cm | L100: 100 | M100: =K100*L100 -> 0 | N100: 2100 | O100: =M100*N100 -> 0
B101: 유칼립투스 | D101: 12 | E101: =C101*D101 -> 0 | G101: =E101*F101 -> 0 | J101: 유칼립투스 | L101: 12 | M101: =K101*L101 -> 0 | O101: =M101*N101 -> 0
B102: 루스커스 | D102: 300 | E102: =C102*D102 -> 0 | G102: =E102*F102 -> 0 | J102: 루스커스 | L102: 300 | M102: =K102*L102 -> 0 | O102: =M102*N102 -> 0
E103: =C103*D103 -> 0 | G103: =E103*F103 -> 0 | M103: =K103*L103 -> 0 | O103: =M103*N103 -> 0
E104: =C104*D104 -> 0 | G104: =E104*F104 -> 0 | M104: =K104*L104 -> 0 | O104: =M104*N104 -> 0
B105: 총계 | G105: =SUM(G98:G104) -> 0 | J105: 총계 | O105: =SUM(O98:O104) -> 0
G106: =G105/1.1 -> 0 | O106: =O105/1.1 -> 0
B108: 일본 | J108: 일본
B109: 품목 | E109: 단 | F109: 가격 | G109: 총계 | J109: 품목 | M109: 단 | N109: 가격 | O109: 총계
B110: Light Pink LL | F110: 14800 | G110: =E110*F110 -> 0 | J110: Light Pink LL | N110: 14800 | O110: =M110*N110 -> 0
B111: Crimson M | F111: 12800 | G111: =E111*F111 -> 0 | H111: 예상가격, 확인 필요 | J111: Crimson M | N111: 12800 | O111: =M111*N111 -> 0 | P111: 예상가격, 확인 필요
B112: Lavender L | F112: 13800 | G112: =E112*F112 -> 0 | J112: Lavender L | N112: 13800 | O112: =M112*N112 -> 0
G113: =E113*F113 -> 0 | O113: =M113*N113 -> 0
G114: =E114*F114 -> 0 | O114: =M114*N114 -> 0
...

Sheet 그외통관비
B3: 백상 창고료 | C3: 460 | H3: 관세
B4: 품목 | C4: 1차 | D4: 2차 | E4: 금액 | F4: 공급가액 | H4: 품목 | I4: 1차 | J4: 2차 | K4: 금액 | L4: 공급가액
B5: 콜롬비아 수국 | C5: 2857 | D5: 1743 | E5: =(C5+D5)*$C$3 -> 2116000 | F5: =E5 -> 2116000 | H5: 콜롬비아 수국 | K5: =I5+J5 -> 0 | L5: =K5 -> 0
B6: 네덜란드 | D6: 491 | E6: =(C6+D6)*$C$3 -> 225860 | F6: =E6 -> 225860 | H6: 네덜란드 | J6: 258260 | K6: =I6+J6 -> 258260 | L6: =K6 -> 258260
B7: 태국 | C7: 137 | E7: =(C7+D7)*$C$3 -> 63020 | F7: =E7 -> 63020 | H7: 태국 | I7: 159500 | K7: =I7+J7 -> 159500 | L7: =K7 -> 159500
B8: 호주 | E8: =(C8+D8)*$C$3 -> 0 | F8: =E8 -> 0 | H8: 호주 | K8: =I8+J8 -> 0 | L8: =K8 -> 0
B9: 미국 | E9: =(C9+D9)*$C$3 -> 0 | F9: =E9 -> 0 | H9: 미국 | K9: =I9+J9 -> 0 | L9: =K9 -> 0
B10: 중국 | C10: 178 | D10: 259 | E10: =(C10+D10)*$C$3 -> 201020 | F10: =E10 -> 201020 | H10: 중국 | I10: 433400 | J10: 687220 | K10: =I10+J10 -> 1120620 | L10: =K10 -> 1120620
B11: 에콰도르 | C11: 104 | E11: =(C11+D11)*$C$3 -> 47840 | F11: =E11 -> 47840 | H11: 에콰도르 | I11: 507900 | K11: =I11+J11 -> 507900 | L11: =K11 -> 507900
B12: 이스라엘 | E12: =(C12+D12)*$C$3 -> 0 | F12: =E12 -> 0 | H12: 이스라엘 | K12: =I12+J12 -> 0 | L12: =K12 -> 0
B13: 뉴질랜드 | E13: =(C13+D13)*$C$3 -> 0 | F13: =E13 -> 0 | H13: 뉴질랜드 | K13: =I13+J13 -> 0 | L13: =K13 -> 0
B14: 일본 | E14: =(C14+D14)*$C$3 -> 0 | F14: =E14 -> 0 | H14: 일본 | K14: =I14+J14 -> 0 | L14: =K14 -> 0
B15: 베트남 | C15: 324 | E15: =(C15+D15)*$C$3 -> 149040 | F15: =E15 -> 149040 | H15: 베트남 | I15: 969990 | K15: =I15+J15 -> 969990 | L15: =K15 -> 969990
B18: 선율 | H18: 월드운송료
B19: 품목 | C19: 1차 | D19: 2차 | E19: 금액 | F19: 공급가액 | H19: 품목 | I19: 1차 | J19: 2차 | K19: 금액 | L19: 공급가액 | N19: 운송비 | O19: 금액
B20: 콜롬비아 수국 | C20: =29700+39600 -> 69300 | D20: =29700+39600 -> 69300 | E20: =C20+D20 -> 138600 | F20: =E20/1.1 -> 126000 | H20: 콜롬비아 수국 | K20: =I20+J20 -> 0 | L20: =K20/1.1 -> 0 | N20: 1t | O20: 99000
B21: 네덜란드 | D21: =29700+108900 -> 138600 | E21: =C21+D21 -> 138600 | F21: =E21/1.1 -> 126000 | H21: 네덜란드 | K21: =I21+J21 -> 0 | L21: =K21/1.1 -> 0 | N21: 2.5t | O21: 187000
B22: 태국 | C22: =29700+39600 -> 69300 | E22: =C22+D22 -> 69300 | F22: =E22/1.1 -> 63000 | H22: 태국 | K22: =I22+J22 -> 0 | L22: =K22/1.1 -> 0 | N22: 5t | O22: 275000
B23: 호주 | E23: =C23+D23 -> 0 | F23: =E23/1.1 -> 0 | H23: 호주 | K23: =I23+J23 -> 0 | L23: =K23/1.1 -> 0
B24: 미국 | E24: =C24+D24 -> 0 | F24: =E24/1.1 -> 0 | H24: 미국 | K24: =I24+J24 -> 0 | L24: =K24/1.1 -> 0
B25: 중국 | C25: =29700+39600 -> 69300 | D25: =29700+59400 -> 89100 | E25: =C25+D25 -> 158400 | F25: =E25/1.1 -> 144000 | H25: 중국 | K25: =I25+J25 -> 0 | L25: =K25/1.1 -> 0
B26: 에콰도르 | C26: =29700+39600 -> 69300 | E26: =C26+D26 -> 69300 | F26: =E26/1.1 -> 63000 | H26: 에콰도르 | K26: =I26+J26 -> 0 | L26: =K26/1.1 -> 0
B27: 이스라엘 | E27: =C27+D27 -> 0 | F27: =E27/1.1 -> 0 | H27: 이스라엘 | K27: =I27+J27 -> 0 | L27: =K27/1.1 -> 0
B28: 뉴질랜드 | E28: =C28+D28 -> 0 | F28: =E28/1.1 -> 0 | H28: 뉴질랜드 | K28: =I28+J28 -> 0 | L28: =K28/1.1 -> 0
B29: 일본 | E29: =C29+D29 -> 0 | F29: =E29/1.1 -> 0 | H29: 일본 | K29: =I29+J29 -> 0 | L29: =K29/1.1 -> 0
B30: 베트남 | C30: =29700+39600 -> 69300 | E30: =C30+D30 -> 69300 | F30: =E30 -> 69300 | H30: 베트남 | K30: =I30+J30 -> 0 | L30: =K30/1.1 -> 0
B33: 한국방역 | H33: 합계
B34: 품목 | C34: 1차 | D34: 2차 | E34: 금액 | F34: 공급가액 | H34: 품목 | I34: 금액
B35: 콜롬비아 수국 | E35: =C35+D35 -> 0 | F35: =E35/1.1 -> 0 | H35: 콜롬비아 수국 | I35: =F5+L5+F20+L20+F35 -> 2242000
B36: 네덜란드 | E36: =C36+D36 -> 0 | F36: =E36/1.1 -> 0 | H36: 네덜란드 | I36: =F6+L6+F21+L21+F36 -> 610120
B37: 태국 | E37: =C37+D37 -> 0 | F37: =E37/1.1 -> 0 | H37: 태국 | I37: =F7+L7+F22+L22+F37 -> 285520
B38: 호주 | C38: 0 | D38: 0 | E38: =C38+D38 -> 0 | F38: =E38/1.1 -> 0 | H38: 호주 | I38: =F8+L8+F23+L23+F38 -> 0
B39: 미국 | C39: 0 | D39: 0 | E39: =C39+D39 -> 0 | F39: =E39/1.1 -> 0 | H39: 미국 | I39: =F9+L9+F24+L24+F39 -> 0
B40: 중국 | E40: =C40+D40 -> 0 | F40: =E40/1.1 -> 0 | H40: 중국 | I40: =F10+L10+F25+L25+F40 -> 1465640
B41: 에콰도르 | E41: =C41+D41 -> 0 | F41: =E41/1.1 -> 0 | H41: 에콰도르 | I41: =F11+L11+F26+L26+F41 -> 618740
B42: 이스라엘 | E42: =C42+D42 -> 0 | F42: =E42/1.1 -> 0 | H42: 이스라엘 | I42: =F12+L12+F27+L27+F42 -> 0
B43: 뉴질랜드 | E43: =C43+D43 -> 0 | F43: =E43/1.1 -> 0 | H43: 뉴질랜드 | I43: =F13+L13+F28+L28+F43 -> 0
B44: 일본 | E44: =C44+D44 -> 0 | F44: =E44/1.1 -> 0 | H44: 일본 | I44: =F14+L14+F29+L29+F44 -> 0
B45: 베트남 | E45: =(C45+D45)*$C$3 -> 0 | F45: =E45 -> 0 | H45: 베트남 | I45: =F15+L15+F30+L30+F45 -> 1188330

Sheet 구매현황
A2: 일자-No. | B2: 거래처명 | C2: 품목명(규격) | D2: 수량 | E2: 박스수량 | F2: 단가 | G2: 외화금액 | H2: 공급가액 | I2: 환율 | J2: 합계 | K2: 차수/품목 | L2: 인보이스넘버 | M2: 결제일
N3: =IF(ISNUMBER(SEARCH("VIETNAM",C3)),"베트남", IF(ISNUMBER(SEARCH("service fee",C3)),IF(ISNUMBER(SEARCH("funza",B3)),"콜롬비아 알스트로",IF(ISNUMBER(SEARCH("INVOS",B3)),"콜롬비아 장미","")), IF(ISNUMBER(SEARCH("CHINA",C3)),"중국", IF(ISNUMBER(SEARCH("ecuador",C3)),"에콰도르", IF(ISNUMBER(SEARCH("ALSTROMERIA",C3)),"콜롬비아 알스트로", IF(ISNUMBER(SEARCH("Banker Bush",C3)),"호주", IF(OR(ISNUMBER(SEARCH("Beargrass",C3)),ISNUMBER(SEARCH("Douglas",C3)),ISNUMBER(SEARCH("SALAL TIPS",C3))),"미국", IF(ISNUMBER(SEARCH("tulip",C3)),"네덜란드", IF(ISNUMBER(SEARCH("sweet pea",C3)),"일본", IF(ISNUMBER(SEARCH("PAEONIA",C3)),"뉴질랜드", IF(ISNUMBER(SEARCH("Hydrangea",C3)),"콜롬비아 수국", IF(ISNUMBER(SEARCH("ruscus",C3)),"콜롬비아 루스커스", IF(OR(ISNUMBER(SEARCH("minicarnation",C3)),ISNUMBER(SEARCH("CARNATION",C3))),"콜롬비아 카네이션", IF(ISNUMBER(SEARCH("rose",C3)),"콜롬비아 장미", IF(ISNUMBER(SEARCH("den",C3)),"태국","")))))))))))))))

Sheet 포워딩
A2: 일자-No. | B2: 거래처명 | C2: 품목명(규격) | D2: 수량 | E2: 박스수량 | F2: 단가 | G2: 외화금액 | H2: 공급가액 | I2: 환율 | J2: 합계 | K2: 차수/품목 | L2: 인보이스넘버 | M2: 결제일
A3: 2026/07/13 -66 | B3: Yunnan Yunyan Flower Industry Development Company Limited | C3: SERVICE FEE | D3: 1 | G3: 3220 | H3: 624068.2 | I3: 193.81 | J3: 624068.2 | K3: 28-1 중C | L3: 93212383 | M3: 선 완 | N3: =IF(ISNUMBER(SEARCH("네",K3)),"네덜란드",IF(ISNUMBER(SEARCH("중",K3)),"중국",IF(ISNUMBER(SEARCH("콜수국",K3)),"콜롬비아 수국",IF(ISNUMBER(SEARCH("에",K3)),"에콰도르",IF(ISNUMBER(SEARCH("태",K3)),"태국",""))))) -> 중국
A4: 2026/07/13 -67 | B4: Yunnan Yunyan Flower Industry Development Company Limited | C4: SERVICE FEE | D4: 1 | G4: 3960.5 | H4: 767584.51 | I4: 193.81 | J4: 767584.51 | K4: 28-2 중C | L4: 93212405 | M4: 선 완 | N4: =IF(ISNUMBER(SEARCH("네",K4)),"네덜란드",IF(ISNUMBER(SEARCH("중",K4)),"중국",IF(ISNUMBER(SEARCH("콜수국",K4)),"콜롬비아 수국",IF(ISNUMBER(SEARCH("에",K4)),"에콰도르",IF(ISNUMBER(SEARCH("태",K4)),"태국",""))))) -> 중국
A5: 2026/07/13 -72 | B5: HOLEX FLOWER B.V. | C5: SERVICE FEE | D5: 1 | G5: 1423.67 | H5: 2153585.6 | I5: 1512.7 | J5: 2153585.6 | K5: 28-1 네H | L5: 4311 | M5: 8/15 | N5: =IF(ISNUMBER(SEARCH("네",K5)),"네덜란드",IF(ISNUMBER(SEARCH("중",K5)),"중국",IF(ISNUMBER(SEARCH("콜수국",K5)),"콜롬비아 수국",IF(ISNUMBER(SEARCH("에",K5)),"에콰도르",IF(ISNUMBER(SEARCH("태",K5)),"태국",""))))) -> 네덜란드
G6: 6417.45 | K6: 28-2 콜수국 | N6: =IF(ISNUMBER(SEARCH("네",K6)),"네덜란드",IF(ISNUMBER(SEARCH("중",K6)),"중국",IF(ISNUMBER(SEARCH("콜수국",K6)),"콜롬비아 수국",IF(ISNUMBER(SEARCH("에",K6)),"에콰도르",IF(ISNUMBER(SEARCH("태",K6)),"태국",""))))) -> 콜롬비아 수국
G7: 9933.6 | K7: 28-1 콜수국 | N7: =IF(ISNUMBER(SEARCH("네",K7)),"네덜란드",IF(ISNUMBER(SEARCH("중",K7)),"중국",IF(ISNUMBER(SEARCH("콜수국",K7)),"콜롬비아 수국",IF(ISNUMBER(SEARCH("에",K7)),"에콰도르",IF(ISNUMBER(SEARCH("태",K7)),"태국",""))))) -> 콜롬비아 수국
G8: 650.43 | K8: 28-1 태국 | N8: =IF(ISNUMBER(SEARCH("네",K8)),"네덜란드",IF(ISNUMBER(SEARCH("중",K8)),"중국",IF(ISNUMBER(SEARCH("콜수국",K8)),"콜롬비아 수국",IF(ISNUMBER(SEARCH("에",K8)),"에콰도르",IF(ISNUMBER(SEARCH("태",K8)),"태국",""))))) -> 태국
G9: 544.45 | K9: 28-1 에콰 | N9: =IF(ISNUMBER(SEARCH("네",K9)),"네덜란드",IF(ISNUMBER(SEARCH("중",K9)),"중국",IF(ISNUMBER(SEARCH("콜수국",K9)),"콜롬비아 수국",IF(ISNUMBER(SEARCH("에",K9)),"에콰도르",IF(ISNUMBER(SEARCH("태",K9)),"태국",""))))) -> 에콰도르
N10: =IF(ISNUMBER(SEARCH("네",K10)),"네덜란드",IF(ISNUMBER(SEARCH("중",K10)),"중국",IF(ISNUMBER(SEARCH("콜수국",K10)),"콜롬비아 수국",IF(ISNUMBER(SEARCH("에",K10)),"에콰도르",IF(ISNUMBER(SEARCH("태",K10)),"태국","")))))
N11: =IF(ISNUMBER(SEARCH("네",K11)),"네덜란드",IF(ISNUMBER(SEARCH("중",K11)),"중국",IF(ISNUMBER(SEARCH("콜수국",K11)),"콜롬비아 수국",IF(ISNUMBER(SEARCH("에",K11)),"에콰도르",IF(ISNUMBER(SEARCH("태",K11)),"태국","")))))
N12: =IF(ISNUMBER(SEARCH("네",K12)),"네덜란드",IF(ISNUMBER(SEARCH("중",K12)),"중국",IF(ISNUMBER(SEARCH("콜수국",K12)),"콜롬비아 수국",IF(ISNUMBER(SEARCH("에",K12)),"에콰도르",IF(ISNUMBER(SEARCH("태",K12)),"태국","")))))
N13: =IF(ISNUMBER(SEARCH("네",K13)),"네덜란드",IF(ISNUMBER(SEARCH("중",K13)),"중국",IF(ISNUMBER(SEARCH("콜수국",K13)),"콜롬비아 수국",IF(ISNUMBER(SEARCH("에",K13)),"에콰도르",IF(ISNUMBER(SEARCH("태",K13)),"태국","")))))
N14: =IF(ISNUMBER(SEARCH("네",K14)),"네덜란드",IF(ISNUMBER(SEARCH("중",K14)),"중국",IF(ISNUMBER(SEARCH("콜수국",K14)),"콜롬비아 수국",IF(ISNUMBER(SEARCH("에",K14)),"에콰도르",IF(ISNUMBER(SEARCH("태",K14)),"태국","")))))
N15: =IF(ISNUMBER(SEARCH("네",K15)),"네덜란드",IF(ISNUMBER(SEARCH("중",K15)),"중국",IF(ISNUMBER(SEARCH("콜수국",K15)),"콜롬비아 수국",IF(ISNUMBER(SEARCH("에",K15)),"에콰도르",IF(ISNUMBER(SEARCH("태",K15)),"태국","")))))
N16: =IF(ISNUMBER(SEARCH("네",K16)),"네덜란드",IF(ISNUMBER(SEARCH("중",K16)),"중국",IF(ISNUMBER(SEARCH("콜수국",K16)),"콜롬비아 수국",IF(ISNUMBER(SEARCH("에",K16)),"에콰도르",IF(ISNUMBER(SEARCH("태",K16)),"태국","")))))
N17: =IF(ISNUMBER(SEARCH("네",K17)),"네덜란드",IF(ISNUMBER(SEARCH("중",K17)),"중국",IF(ISNUMBER(SEARCH("콜수국",K17)),"콜롬비아 수국",IF(ISNUMBER(SEARCH("에",K17)),"에콰도르",IF(ISNUMBER(SEARCH("태",K17)),"태국","")))))

Sheet 판매현황
A3: 거래처 | B3: 품목별 | C3: 수량 | D3: 단가 | E3: 공급가액 | F3: 부가세 | G3: 합계 | I3: 품명
I4: =IFERROR(IF(INDEX(품목리스트!$E$2:$E$9000,MATCH(TRIM(SUBSTITUTE(SUBSTITUTE(SUBSTITUTE(CLEAN(B4)," 계",""),"계",""),CHAR(160)," "))&"*",TRIM(SUBSTITUTE(SUBSTITUTE(CLEAN(품목리스트!$C$2:$C$9000),CHAR(160)," "),CHAR(9)," ")),0))="콜롬비아",IF(ISNUMBER(SEARCH("Hydrangea",B4)),"콜롬비아 수국",IF(ISNUMBER(SEARCH("carnation",B4)),"콜롬비아 카네이션",IF(ISNUMBER(SEARCH("Rose",B4)),"콜롬비아 장미",IF(ISNUMBER(SEARCH("ruscus",B4)),"콜롬비아 루스커스",IF(ISNUMBER(SEARCH("ALSTROMERIA",B4)),"콜롬비아 알스트로","콜롬비아"))))),INDEX(품목리스트!$E$2:$E$9000,MATCH(TRIM(SUBSTITUTE(SUBSTITUTE(SUBSTITUTE(CLEAN(B4)," 계",""),"계",""),CHAR(160)," "))&"*",TRIM(SUBSTITUTE(SUBSTITUTE(CLEAN(품목리스트!$C$2:$C$9000),CHAR(160)," "),CHAR(9)," ")),0))),IF(ISNUMBER(SEARCH("ALSTROMERIA",B4)),"콜롬비아 알스트로",IF(ISNUMBER(SEARCH("Den.",B4)),"태국",IF(ISNUMBER(SEARCH("CHINA",B4)),"중국",IF(AND(ISNUMBER(SEARCH("rose",B4)),NOT(ISNUMBER(SEARCH("CHINA",B4)))),"콜롬비아 장미",IF(AND(ISNUMBER(SEARCH("carnation",B4)),NOT(ISNUMBER(SEARCH("CHINA",B4)))),"콜롬비아 카네이션",IF(ISNUMBER(SEARCH("Peony",B4)),"뉴질랜드",IF(ISNUMBER(SEARCH("Amaryllis",B4)),"네덜란드",IF(ISNUMBER(SEARCH("Sweet pea",B4)),"일본","")))))))))
H32: 7/13
H33: 7/13
H34: 7/13
H35: 7/13
H45: 7/13
H77: 7/7 출고건 포함
H80: 7/7 출고건 포함
H87: 27차 추가분 - 1박스
H95: 7/7 출고건 포함
H153: 7/7출고건
H158: 7/7출고건
K213: 255
H244: 7/7 출고건 포함
H251: 27차 추가분 - 1박스
H256: 7/7 출고건 포함
H364: 7/13
H367: 7/13
H368: 7/13
H574: 위탁판매건
H635: 위탁판매요청
H710: 7/13
H724: 7/13
H725: 7/13

Sheet 불량차감
A2: 일자-No. | B2: 거래처명 | C2: 품목명 | D2: 수량 | E2: 단가(vat포함) | F2: 공급가액 | G2: 부가세 | H2: 합계 | I2: 적요
J3: =IFERROR(IF(INDEX(품목리스트!$E$2:$E$3000,MATCH(TRIM(SUBSTITUTE(SUBSTITUTE(SUBSTITUTE(CLEAN(I3)," 계",""),"계",""),CHAR(160)," "))&"*",TRIM(SUBSTITUTE(SUBSTITUTE(CLEAN(품목리스트!$C$2:$C$3000),CHAR(160)," "),CHAR(9)," ")),0))="콜롬비아",IF(ISNUMBER(SEARCH("Hydrangea",I3)),"콜롬비아 수국",IF(ISNUMBER(SEARCH("carnation",I3)),"콜롬비아 카네이션",IF(ISNUMBER(SEARCH("Rose",I3)),"콜롬비아 장미",IF(ISNUMBER(SEARCH("ruscus",I3)),"콜롬비아 루스커스",IF(ISNUMBER(SEARCH("ALSTROMERIA",I3)),"콜롬비아 알스트로","콜롬비아"))))),INDEX(품목리스트!$E$2:$E$3000,MATCH(TRIM(SUBSTITUTE(SUBSTITUTE(SUBSTITUTE(CLEAN(I3)," 계",""),"계",""),CHAR(160)," "))&"*",TRIM(SUBSTITUTE(SUBSTITUTE(CLEAN(품목리스트!$C$2:$C$3000),CHAR(160)," "),CHAR(9)," ")),0))),IF(ISNUMBER(SEARCH("ALSTROMERIA",I3)),"콜롬비아 알스트로",IF(ISNUMBER(SEARCH("Den.",I3)),"태국",IF(ISNUMBER(SEARCH("CHINA",I3)),"중국",IF(AND(ISNUMBER(SEARCH("rose",I3)),NOT(ISNUMBER(SEARCH("CHINA",I3)))),"콜롬비아 장미",IF(AND(ISNUMBER(SEARCH("carnation",I3)),NOT(ISNUMBER(SEARCH("CHINA",I3)))),"콜롬비아 카네이션",IF(ISNUMBER(SEARCH("Peony",I3)),"뉴질랜드",IF(ISNUMBER(SEARCH("Amaryllis",I3)),"네덜란드",IF(ISNUMBER(SEARCH("Sweet pea",I3)),"일본","")))))))))

Sheet 그 외 매출액
A2: 일자-No. | B2: 거래처명 | C2: 품목명 | D2: 수량 | E2: 단가(vat포함) | F2: 공급가액 | G2: 부가세 | H2: 합계 | I2: 적요
J3: =IF(ISNUMBER(SEARCH("현지상차운임",I3)),"콜롬비아 수국",IF(ISNUMBER(SEARCH("현지상차운임",C3)),"콜롬비아 수국",IF(ISNUMBER(SEARCH("루스커스 운송료",C3)),"콜롬비아 루스커스",IF(ISNUMBER(SEARCH("카네이션 운송료",C3)),"콜롬비아 카네이션",IF(ISNUMBER(SEARCH("장미 운송료",C3)),"콜롬비아 장미",IF(ISNUMBER(SEARCH("수국 운송료",C3)),"콜롬비아 수국",IF(ISNUMBER(SEARCH("중국 운송료",C3)),"중국",IF(ISNUMBER(SEARCH("태국 운송료",C3)),"태국",IF(ISNUMBER(SEARCH("레몬잎 운송료",C3)),"미국",IF(ISNUMBER(SEARCH("네덜란드 운송료",C3)),"네덜란드",IF(ISNUMBER(SEARCH("호주 운송료",C3)),"호주",IFERROR(IF(INDEX(품목리스트!$E$2:$E$9000,MATCH(TRIM(SUBSTITUTE(SUBSTITUTE(SUBSTITUTE(CLEAN(I3)," 계",""),"계",""),CHAR(160)," "))&"*",TRIM(SUBSTITUTE(SUBSTITUTE(CLEAN(품목리스트!$C$2:$C$9000),CHAR(160)," "),CHAR(9)," ")),0))="콜롬비아",IF(ISNUMBER(SEARCH("Hydrangea",I3)),"콜롬비아 수국",IF(ISNUMBER(SEARCH("carnation",I3)),"콜롬비아 카네이션",IF(ISNUMBER(SEARCH("Rose",I3)),"콜롬비아 장미",IF(ISNUMBER(SEARCH("ruscus",I3)),"콜롬비아 루스커스",IF(ISNUMBER(SEARCH("ALSTROMERIA",I3)),"콜롬비아 알스트로","콜롬비아"))))),INDEX(품목리스트!$E$2:$E$9000,MATCH(TRIM(SUBSTITUTE(SUBSTITUTE(SUBSTITUTE(CLEAN(I3)," 계",""),"계",""),CHAR(160)," "))&"*",TRIM(SUBSTITUTE(SUBSTITUTE(CLEAN(품목리스트!$C$2:$C$9000),CHAR(160)," "),CHAR(9)," ")),0))),IF(ISNUMBER(SEARCH("ALSTROMERIA",I3)),"콜롬비아 알스트로",IF(ISNUMBER(SEARCH("Den.",I3)),"태국",IF(ISNUMBER(SEARCH("CHINA",I3)),"중국",IF(AND(ISNUMBER(SEARCH("rose",I3)),NOT(ISNUMBER(SEARCH("CHINA",I3)))),"콜롬비아 장미",IF(AND(ISNUMBER(SEARCH("carnation",I3)),NOT(ISNUMBER(SEARCH("CHINA",I3)))),"콜롬비아 카네이션",IF(ISNUMBER(SEARCH("Peony",I3)),"뉴질랜드",IF(ISNUMBER(SEARCH("Amaryllis",I3)),"네덜란드",IF(ISNUMBER(SEARCH("Sweet pea",I3)),"일본",""))))))))))))))))))))

Sheet 콜롬비아 1차
B2: 콜롬비아 사후원가 28-1차
B4: 환율 | D4: ='주차별 매출이익 보고서'!R8 -> 1548.52 | G4: 운송비 | H4: 금액 | I4: 대
G5: 1t | H5: 99000
B6: 항공료 | D6: 20472.84 | G6: 2.5t | H6: 187000
G7: 5t | H7: 275000 | I7: 1
B9: 통관비 (DETAIL)
B10: 창고비 (백상) | C10: =E10*460 -> 3501980 | D10: Gross W | E10: 7613 | G10: 품목 | H10: 차감 stems | I10: 검역 차감액
B11: 통관수수료 (선율) | C11: 33000 | G11: 장미
B12: 검역대행수수료 (선율) | C12: =E12*10000 -> 40000 | D12: 품목수 | E12: 4 | G12: 알스트로
B13: 운송비 (월드종합운수) | C13: =(I5*H5)+(I6*H6)+(I7*H7) -> 275000 | G13: 카네이션
B14: 관세료 | G14: 미니카네이션
B15: 소독비용 | G15: 미니 장미
B16: 검역비용 | C16: =(H11*I11)+(H12*I12)+(H13*I13)+(H14*I14)+(H15*I15)+(H16*I16) -> 0 | G16: 루스쿠스
B17: TOTAL | C17: =SUBTOTAL(9,C10:C16) -> 3849980
B20: 농장 | E20: 총인보이스 금액 | F20: 항공료 | G20: CNF 원화 | H20: 그 외 통관비 | K20: 도착 금액 | L20: 판매금액 | M20: 이익금 | N20: 이익률
B21: 장미 | E21: =C31 -> 0 | F21: =IF($L$29=$L$30,$D$6*M37,$D$6*R37) -> 3627.3249 | H21: =$C$17*M37 -> 682129.51 | M21: =+L21-K21 -> 0 | N21: =+M21/L21 -> #DIV/0!
B22: 카네이션 | E22: =D31 -> 0 | F22: =IF($L$29=$L$30,$D$6*M38,$D$6*R38) -> 14730.212 | H22: =$C$17*M38 -> 2770061.3 | M22: =+L22-K22 -> 0 | N22: =+M22/L22 -> #DIV/0!
B23: 알스트로 | E23: =E31 -> 0 | F23: =IF($L$29=$L$30,$D$6*M39,$D$6*R39) -> 740.73793 | H23: =$C$17*M39 -> 139298.03 | M23: =+L23-K23 -> 0 | N23: =+M23/L23 -> #DIV/0!
B24: 루스커스 | E24: =F31 -> 0 | F24: =IF($L$29=$L$30,$D$6*M40,$D$6*R40) -> 1374.5652 | H24: =$C$17*M40 -> 258491.18 | M24: =+L24-K24 -> 0 | N24: =+M24/L24 -> #DIV/0!
K29: CW | L29: 7613
C30: 장미 | D30: 카네이션 | E30: 알스토로 | F30: 류스쿠스 | K30: GW | L30: 7613
B31: 인보이스 총금액 | C31: =SUM(C32:C70) -> 0 | D31: =SUM(D32:D70) -> 0 | E31: =SUM(E32:E70) -> 0 | F31: =SUM(F32:F70) -> 0
B32: APOSENTOS | J32: 운성비 풍목벽 분배 비율 계산
B33: AYURA | J33: GW==CW | K33: 무게로 계산 될 때 | O33: GW << CW | P33: CBM으로 계산 될 때
B34: BENCHMARK
B35: CACTUS | J35: 한공료 분배 | O35: 한공료 분배
B36: CIRCASIA | K36: 박스당 무게 | L36: 박스 수량 | M36: 비율 | P36: 박스당 CBM | Q36: 박스 수량 | R36: 비율
B37: COLIBRI | J37: 장미 | K37: 7 | L37: 190 | M37: =K37*L37/($K$37*$L$37+$K$38*$L$38+$K$39*$L$39+$K$40*$L$40) -> 0.17717742 | O37: 장미 | P37: 10 | Q37: 190 | R37: =(P37*Q37)/($P$37*$Q$37+$P$38*$Q$38+$P$39*$Q$39+$P$40*$Q$40) -> 0.23451579
B38: CONSTRUNORTE | J38: 카네이션 | K38: 11 | L38: 491 | M38: =K38*L38/($K$37*$L$37+$K$38*$L$38+$K$39*$L$39+$K$40*$L$40) -> 0.71950017 | O38: 카네이션 | P38: 11 | Q38: 491 | R38: =(P38*Q38)/($P$37*$Q$37+$P$38*$Q$38+$P$39*$Q$39+$P$40*$Q$40) -> 0.66664198
B39: DON EUSEBIO | J39: 알스트로 | K39: 9.7 | L39: 28 | M39: =K39*L39/($K$37*$L$37+$K$38*$L$38+$K$39*$L$39+$K$40*$L$40) -> 0.036181494 | O39: 알스트로 | P39: 7 | Q39: 28 | R39: =(P39*Q39)/($P$37*$Q$37+$P$38*$Q$38+$P$39*$Q$39+$P$40*$Q$40) -> 0.024192155
B40: ESPERANCE | J40: 루스코스 | K40: 8 | L40: 63 | M40: =K40*L40/($K$37*$L$37+$K$38*$L$38+$K$39*$L$39+$K$40*$L$40) -> 0.067140916 | O40: 루스코스 | P40: 9.6 | Q40: 63 | R40: =(P40*Q40)/($P$37*$Q$37+$P$38*$Q$38+$P$39*$Q$39+$P$40*$Q$40) -> 0.074650078
B41: FILCO | M41: =SUM(M37:M40) -> 1 | R41: =SUM(R37:R40) -> 1
B42: FIORI
B43: FLORA
B44: FUNZA
B45: GAITANA
B46: GAMBUR
B47: INVERPALMAS
B48: INVOS
B49: MAXIFLORES
B50: MILAGRO
B51: MONIKA
B52: NATUR
B53: PONDEROZA
... B70: ZORRO

Sheet 콜롬비아 2차
B2: 콜롬비아 사후원가 28-2차
B4: 환율 | D4: ='주차별 매출이익 보고서'!R8 -> 1548.52 | G4: 운송비 | H4: 금액 | I4: 대
G5: 1t | H5: 99000
B6: 항공료 | D6: 5687.39 | G6: 2.5t | H6: 187000 | I6: 1
G7: 5t | H7: 275000
B9: 통관비 (DETAIL)
B10: 창고비 (백상) | C10: =E10*460 -> 939780 | D10: Gross W | E10: 2043 | G10: 품목 | H10: 차감 stems | I10: 검역 차감액
B11: 통관수수료 (선율) | C11: 33000 | G11: 장미
B12: 검역대행수수료 (선율) | C12: =E12*10000 -> 40000 | D12: 품목수 | E12: 4 | G12: 알스트로
B13: 운송비 (월드종합운수) | C13: =(I5*H5)+(I6*H6)+(I7*H7) -> 187000 | G13: 카네이션
B14: 관세료 | G14: 미니카네이션
B15: 소독비용 | G15: 미니 장미
B16: 검역비용 | C16: =(H11*I11)+(H12*I12)+(H13*I13)+(H14*I14)+(H15*I15)+(H16*I16) -> 0 | G16: 루스쿠스
B17: TOTAL | C17: =SUBTOTAL(9,C10:C16) -> 1199780
B20: 농장 | E20: 총인보이스 금액 | F20: 항공료 | G20: CNF 원화 | H20: 그 외 통관비 | K20: 도착 금액 | L20: 판매금액 | M20: 이익금 | N20: 이익률
B21: 장미 | E21: =C31 -> 0 | F21: =IF($L$29=$L$30,$D$6*M37,$D$6*R37) -> 1815.3644 | G21: =SUM(E21:F21)*$D$4 -> 2811128 | H21: =$C$17*M37 -> 382959.12 | K21: =G21+H21+I21+J21 -> 3194087.2 | M21: =+L21-K21 -> -3194087.2 | N21: =+M21/L21 -> #DIV/0!
B22: 카네이션 | E22: =D31 -> 0 | F22: =IF($L$29=$L$30,$D$6*M38,$D$6*R38) -> 3379.8476 | G22: =SUM(E22:F22)*$D$4 -> 5233761.7 | H22: =$C$17*M38 -> 712993.76 | K22: =G22+H22+I22+J22 -> 5946755.4 | M22: =+L22-K22 -> -5946755.4 | N22: =+M22/L22 -> #DIV/0!
B23: 알스트로 | E23: =E31 -> 0 | F23: =IF($L$29=$L$30,$D$6*M39,$D$6*R39) -> 492.17798 | G23: =SUM(E23:F23)*$D$4 -> 762147.45 | H23: =$C$17*M39 -> 103827.12 | K23: =G23+H23+I23+J23 -> 865974.56 | M23: =+L23-K23 -> -865974.56 | N23: =+M23/L23 -> #DIV/0!
B24: 루스커스 | E24: =F31 -> 0 | F24: =IF($L$29=$L$30,$D$6*M40,$D$6*R40) -> 0 | G24: =SUM(E24:F24)*$D$4 -> 0 | H24: =$C$17*M40 -> 0 | K24: =G24+H24+I24+J24 -> 0 | M24: =+L24-K24 -> 0 | N24: =+M24/L24 -> #DIV/0!
K29: CW | L29: 2043
C30: 장미 | D30: 카네이션 | E30: 알스토로 | F30: 류스쿠스 | K30: GW | L30: 2043
B31: 인보이스 총금액 | C31: =SUM(C32:C73) -> 0 | D31: =SUM(D32:D73) -> 0 | E31: =SUM(E32:E73) -> 0 | F31: =SUM(F32:F73) -> 0
B32: APOSENTOS | J32: 운성비 풍목벽 분배 비율 계산
B33: AYURA | J33: GW==CW | K33: 무게로 계산 될 때 | O33: GW << CW | P33: CBM으로 계산 될 때
B34: AURORA
B35: BENCHMARK | J35: 한공료 분배 | O35: 한공료 분배
B36: CACTUS | K36: 박스당 무게 | L36: 박스 수량 | M36: 비율 | P36: 박스당 CBM | Q36: 박스 수량 | R36: 비율
B37: CIRCASIA | J37: 장미 | K37: 7 | L37: 92 | M37: =K37*L37/($K$37*$L$37+$K$38*$L$38+$K$39*$L$39+$K$40*$L$40) -> 0.31919112 | O37: 장미 | P37: 10 | Q37: 92 | R37: =(P37*Q37)/($P$37*$Q$37+$P$38*$Q$38+$P$39*$Q$39+$P$40*$Q$40) -> 0.40979955
B38: COLIBRI | J38: 카네이션 | K38: 11 | L38: 109 | M38: =K38*L38/($K$37*$L$37+$K$38*$L$38+$K$39*$L$39+$K$40*$L$40) -> 0.59427042 | O38: 카네이션 | P38: 11 | Q38: 109 | R38: =(P38*Q38)/($P$37*$Q$37+$P$38*$Q$38+$P$39*$Q$39+$P$40*$Q$40) -> 0.53407572
B39: CONSTRUNORTE | J39: 알스트로 | K39: 9.7 | L39: 18 | M39: =K39*L39/($K$37*$L$37+$K$38*$L$38+$K$39*$L$39+$K$40*$L$40) -> 0.086538462 | O39: 알스트로 | P39: 7 | Q39: 18 | R39: =(P39*Q39)/($P$37*$Q$37+$P$38*$Q$38+$P$39*$Q$39+$P$40*$Q$40) -> 0.056124722
B40: DAFLOR | J40: 루스코스 | K40: 8 | M40: =K40*L40/($K$37*$L$37+$K$38*$L$38+$K$39*$L$39+$K$40*$L$40) -> 0 | O40: 루스코스 | P40: 9.6 | R40: =(P40*Q40)/($P$37*$Q$37+$P$38*$Q$38+$P$39*$Q$39+$P$40*$Q$40) -> 0
B41: DON EUSEBIO | M41: =SUM(M37:M40) -> 1 | R41: =SUM(R37:R40) -> 1
B42: ESPERANCE
B43: FILCO
B44: FIORI
B45: FLORA
B46: FUNZA
B47: GAITANA
B48: GAMBUR
B49: INVERPALMAS
B50: INVOS
B51: MAXIFLORES
B52: MILAGRO
B53: MONIKA
... B73: ZORRO

Sheet 품목리스트
A1: 품목번호 | B1: 품목코드 | C1: 품목명 | D1: 꽃 | E1: 국가 | F1: 출고단가 | G1: 출고단위 | H1: 견적단위 | I1: 비고
A2: 1 | B2: ACA01-NL0001 | C2: Acasia / Chiara de Luna | D2: 아카시아 | E2: 네덜란드 | F2: 0 | G2: 단 | H2: 단
A3: 2 | B3: ACA01-NL0002 | C3: Acasia / Denis Boden | D3: 아카시아 | E3: 네덜란드 | F3: 0 | G3: 단 | H3: 단
A4: 3 | B4: ACA01-NL0003 | C4: Acasia / Hamburyana | D4: 아카시아 | E4: 네덜란드 | F4: 0 | G4: 단 | H4: 단
A5: 4 | B5: ACA01-NL0004 | C5: Acasia / Luna Arg | D5: 아카시아 | E5: 네덜란드 | F5: 0 | G5: 단 | H5: 단
A6: 5 | B6: ACA01-NL0005 | C6: Acasia / Mimosa Baileyana 500g | D6: 아카시아 | E6: 네덜란드 | F6: 0 | G6: 단 | H6: 단
A7: 6 | B7: ACA01-NL0006 | C7: Acasia / Mimosa Floribunda 150g | D7: 아카시아 | E7: 네덜란드 | F7: 0 | G7: 단 | H7: 단
A8: 7 | B8: ACA01-NL0007 | C8: Acasia / Mimosa Floribunda 400g | D8: 아카시아 | E8: 네덜란드 | F8: 0 | G8: 단 | H8: 단
A9: 8 | B9: ACA01-NL0008 | C9: Acasia / Mimosa Mirandol 200g | D9: 아카시아 | E9: 네덜란드 | F9: 0 | G9: 단 | H9: 단
A10: 9 | B10: ACA01-NL0009 | C10: Acasia / Mimosa Retinodes | D10: 아카시아 | E10: 네덜란드 | F10: 0 | G10: 단 | H10: 단
A11: 10 | B11: ACA01-NL0010 | C11: Acasia / Mimosa Rups 200g | D11: 아카시아 | E11: 네덜란드 | F11: 0 | G11: 단 | H11: 단
A12: 11 | B12: ACA01-NL0011 | C12: Acasia / Mimosa Rups 400g | D12: 아카시아 | E12: 네덜란드 | F12: 0 | G12: 단 | H12: 단
A13: 12 | B13: ACA01-NL0012 | C13: Acasia / Mimosa Turner Green 250g | D13: 아카시아 | E13: 네덜란드 | F13: 0 | G13: 단 | H13: 단
... A22: 21 | B22: AGA01-NL0003 | C22: Agapanthus / Bianca Perla White 70cm | D22: 아가판서스 | E22: 네덜란드 | F22: 0 | G22: 송이 | H22: 송이
A23: 22 | B23: AGA01-NL0004 | C23: Agapanthus / Eyfori Blue 70cm | D23: 아가판서스 | E23: 네덜란드 | F23: 0 | G23: 송이 | H23: 송이 | I23: 블루/MoQ x20
A24: 23 | B24: AGA01-NL0005 | C24: Agapanthus / Eyfori White 70cm | D24: 아가판서스 | E24: 네덜란드 | F24: 0 | G24: 송이 | H24: 송이 | I24: 화이트／MoQ x20
A25: 24 | B25: AGA01-NL0006 | C25: Agapanthus / Eyfori White 90cm | D25: 아가판서스 | E25: 네덜란드 | F25: 0 | G25: 송이 | H25: 송이
A26: 25 | B26: AGA01-NL0007 | C26: Agapanthus / Gletsjer | D26: 아가판서스 | E26: 네덜란드 | F26: 0 | G26: 송이 | H26: 송이 | I26: MoQ x20
A27: 26 | B27: AGA01-NL0008 | C27: Agapanthus / White Grace 80cm | D27: 아가판서스 | E27: 네덜란드 | F27: 0 | G27: 송이 | H27: 송이
A28: 27 | B28: AGA01-NL0009 | C28: Agapanthus / Susan 85cm | D28: 아가판서스 | E28: 네덜란드 | F28: 0 | G28: 송이 | H28: 송이
A29: 28 | B29: AGA01-NL0010 | C29: Agapanthus / White Barcelona 75cm | D29: 아가판서스 | E29: 네덜란드 | F29: 0 | G29: 송이 | H29: 송이
A30: 29 | B30: AGA01-NL0011 | C30: Agapanthus / Queen of the ocean 80cm | D30: 아가판서스 | E30: 네덜란드 | F30: 0 | G30: 송이 | H30: 송이
A31: 30 | B31: AGA01-NL0012 | C31: Agapanthus / Uri | D31: 아가판서스 | E31: 네덜란드 | F31: 0 | G31: 송이 | H31: 송이 | I31: 보라／MoQ x20
A32: 31 | B32: ALL01-NL0001 | C32: Allium / Ambassador | D32: 알륨 | E32: 네덜란드 | F32: 0 | G32: 송이 | H32: 송이
A33: 32 | B33: ALL01-NL0002 | C33: Allium / Giganteum | D33: 알륨 | E33: 네덜란드 | F33: 0 | G33: 송이 | H33: 송이 | I33: MoQ x30/보라/
A34: 33 | B34: ALL01-NL0003 | C34: Allium / Molly Yellow | D34: 알륨 | E34: 네덜란드 | F34: 0 | G34: 송이 | H34: 송이
A35: 34 | B35: ALL01-NL0004 | C35: Allium / Mount Everest Pink | D35: 알륨 | E35: 네덜란드 | F35: 0 | G35: 송이 | H35: 송이
A36: 35 | B36: ALL01-NL0005 | C36: Allium / Mount Everest White | D36: 알륨 | E36: 네덜란드 | F36: 0 | G36: 송이 | H36: 송이 | I36: 화이트／시즌 5월-7월 MoQ x20
A37: 36 | B37: ALL01-NL0006 | C37: Allium / Nectaroscordum Rosy Bells | D37: 알륨 | E37: 네덜란드 | F37: 0 | G37: 송이 | H37: 송이 | I37: 핑크/
A38: 37 | B38: ALL01-NL0007 | C38: Allium / Siculum Bulgar | D38: 알륨 | E38: 네덜란드 | F38: 0 | G38: 송이 | H38: 송이
A39: 38 | B39: ALL01-NL0008 | C39: Allium / White Giant | D39: 알륨 | E39: 네덜란드 | F39: 0 | G39: 송이 | H39: 송이 | I39: MoQ x10/화이트/
A40: 39 | B40: ALL01-NL0009 | C40: Allium / Gladiator | D40: 알륨 | E40: 네덜란드 | F40: 0 | G40: 송이 | H40: 송이 | I40: 보라／시즌 4월- 7월 MoQ x20
A41: 40 | B41: ALL01-NL0010 | C41: Allium / Silverspring | D41: 알륨 | E41: 네덜란드 | F41: 0 | G41: 송이 | H41: 송이
A42: 41 | B42: ALL01-NL0011 | C42: Allium / Miami | D42: 알륨 | E42: 네덜란드 | F42: 0 | G42: 송이 | H42: 송이
A43: 42 | B43: ALL01-NL0012 | C43: Allium / Schubertii | D43: 알륨 | E43: 네덜란드 | F43: 0 | G43: 송이 | H43: 송이 | I43: 핑크／
A44: 44 | B44: ALL01-NL0014 | C44: Allium / Pink Jewel | D44: 알륨 | E44: 네덜란드 | F44: 0 | G44: 송이 | H44: 송이
A45: 46 | B45: ALL01-NL0016 | C45: Allium / Bullit | D45: 알륨 | E45: 네덜란드 | F45: 0 | G45: 송이 | H45: 송이
A46: 47 | B46: ALS01-CO0001 | C46: ALSTROMERIA ORANGE | D46: 알스트로 | E46: 콜롬비아 | F46: 0 | G46: 단 | H46: 송이
A47: 48 | B47: ALS01-CO0002 | C47: ALSTROMERIA Pink | D47: 알스트로 | E47: 콜롬비아 | F47: 0 | G47: 단 | H47: 송이
A48: 49 | B48: ALS01-CO0003 | C48: ALSTROMERIA WHITE | D48: 알스트로 | E48: 콜롬비아 | F48: 0 | G48: 단 | H48: 송이
A49: 50 | B49: ALS01-CO0004 | C49: ALSTROMERIA YELLOW | D49: 알스트로 | E49: 콜롬비아 | F49: 0 | G49: 단 | H49: 송이
A50: 53 | B50: ALS01-CO0007 | C50: ALSTROMERIA Whistler | D50: 알스트로 | E50: 콜롬비아 | F50: 650 | G50: 단 | H50: 송이
A51: 54 | B51: ALS01-CO0008 | C51: ALSTROMERIA Dubai | D51: 알스트로 | E51: 콜롬비아 | F51: 650 | G51: 단 | H51: 송이
A52: 55 | B52: ALS01-CO0009 | C52: ALSTROMERIA Prima Donna | D52: 알스트로 | E52: 콜롬비아 | F52: 0 | G52: 단 | H52: 송이
A53: 56 | B53: ALS01-CO0010 | C53: ALSTROMERIA Costa | D53: 알스트로 | E53: 콜롬비아 | F53: 0 | G53: 단 | H53: 송이
A54: 57 | B54: ALS01-CO0011 | C54: ALSTROMERIA Cheescake | D54: 알스트로 | E54: 콜롬비아 | F54: 0 | G54: 단 | H54: 송이
A55: 58 | B55: ALS01-CO0012 | C55: ALSTROMERIA Cream | D55: 알스트로 | E55: 콜롬비아 | F55: 0 | G55: 단 | H55: 송이
... A100: 106 | B100: AMA01-NL0005 | C100: Amaryllis / Britney | D100: 아마릴리스 | E100: 네덜란드 | F100: 0 | G100: 송이 | H100: 송이
A101: 107 | B101: AMA01-NL0006 | C101: Amaryllis / Casablanca 12st White1 | D101: 아마릴리스 | E101: 네덜란드 | F101: 0 | G101: 송이 | H101: 송이 | I101: 시즌 10월중 - 07월중
A102: 108 | B102: AMA01-NL0007 | C102: Amaryllis / Casablanca 15st White2 | D102: 아마릴리스 | E102: 네덜란드 | F102: 0 | G102: 송이 | H102: 송이 | I102: 시즌 10월중 - 07월중
A103: 109 | B103: AMA01-NL0008 | C103: Amaryllis / Darling | D103: 아마릴리스 | E103: 네덜란드 | F103: 0 | G103: 송이 | H103: 송이 | I103: 시즌 10월중 - 07월중
A104: 110 | B104: AMA01-NL0009 | C104: Amaryllis / Desire | D104: 아마릴리스 | E104: 네덜란드 | F104: 0 | G104: 송이 | H104: 송이 | I104: 시즌 10월중 - 07월중
A105: 111 | B105: AMA01-NL0010 | C105: Amaryllis / Ferrari | D105: 아마릴리스 | E105: 네덜란드 | F105: 0 | G105: 송이 | H105: 송이 | I105: 시즌 10월중 - 07월중
A106: 112 | B106: AMA01-NL0011 | C106: Amaryllis / Gold Medal | D106: 아마릴리스 | E106: 네덜란드 | F106: 0 | G106: 송이 | H106: 송이
A107: 113 | B107: AMA01-NL0012 | C107: Amaryllis / Hercules | D107: 아마릴리스 | E107: 네덜란드 | F107: 0 | G107: 송이 | H107: 송이
A108: 114 | B108: AMA01-NL0013 | C108: Amaryllis / Loyalty | D108: 아마릴리스 | E108: 네덜란드 | F108: 0 | G108: 송이 | H108: 송이
A109: 115 | B109: AMA01-NL0014 | C109: Amaryllis / Mont Blanc 10st White1 | D109: 아마릴리스 | E109: 네덜란드 | F109: 0 | G109: 송이 | H109: 송이 | I109: 시즌 10월중 - 07월중
A110: 116 | B110: AMA01-NL0015 | C110: Amaryllis / Mont Blanc 12st White | D110: 아마릴리스 | E110: 네덜란드 | F110: 0 | G110: 송이 | H110: 송이 | I110: 화이트／시즌 10월중 - 07월중
A111: 117 | B111: AMA01-NL0016 | C111: Amaryllis / Naranja | D111: 아마릴리스 | E111: 네덜란드 | F111: 0 | G111: 송이 | H111: 송이
A112: 118 | B112: AMA01-NL0017 | C112: Amaryllis / Red Lion12st | D112: 아마릴리스 | E112: 네덜란드 | F112: 0 | G112: 송이 | H112: 송이 | I112: 시즌 10월중 - 02월중
A113: 119 | B113: AMA01-NL0018 | C113: Amaryllis / Rilona (Salmon) 12st | D113: 아마릴리스 | E113: 네덜란드 | F113: 0 | G113: 송이 | H113: 송이 | I113: 시즌 10월중 - 07월중
A114: 120 | B114: AMA01-NL0019 | C114: Amaryllis / Rilona 18st | D114: 아마릴리스 | E114: 네덜란드 | F114: 0 | G114: 송이 | H114: 송이
A115: 121 | B115: AMA01-NL0020 | C115: Amaryllis / Van der Ende Orange | D115: 아마릴리스 | E115: 네덜란드 | F115: 0 | G115: 송이 | H115: 송이
A116: 122 | B116: AMA01-NL0021 | C116: Amaryllis / Mont Blanc 15st White | D116: 아마릴리스 | E116: 네덜란드 | F116: 0 | G116: 송이 | H116: 송이
A117: 123 | B117: AMA01-NL0022 | C117: Amaryllis / Rilona (Salmon) 15st | D117: 아마릴리스 | E117: 네덜란드 | F117: 0 | G117: 송이 | H117: 송이
A118: 124 | B118: AMA01-NL0023 | C118: Amaryllis / Red Lion15st | D118: 아마릴리스 | E118: 네덜란드 | F118: 0 | G118: 송이 | H118: 송이
A119: 125 | B119: AMA01-NL0024 | C119: Amaryllis / Wild Amazone | D119: 아마릴리스 | E119: 네덜란드 | F119: 0 | G119: 송이 | H119: 송이
A120: 126 | B120: AMA01-NL0025 | C120: Amaryllis / Pink Amazone | D120: 아마릴리스 | E120: 네덜란드 | F120: 0 | G120: 송이 | H120: 송이
A121: 127 | B121: AMA01-NL0026 | C121: Amaryllis / Casa Blanc 15st White | D121: 아마릴리스 | E121: 네덜란드 | F121: 0 | G121: 송이 | H121: 송이
A122: 128 | B122: AMA01-NL0027 | C122: Amaryllis / Boquet 12st | D122: 아마릴리스 | E122: 네덜란드 | F122: 0 | G122: 송이 | H122: 송이
A123: 130 | B123: AMA01-NL0029 | C123: Amaryllis / Red Liberty 12st | D123: 아마릴리스 | E123: 네덜란드 | F123: 0 | G123: 송이 | H123: 송이
A124: 131 | B124: AMA01-NL0030 | C124: Amaryllis / Royal Velvet | D124: 아마릴리스 | E124: 네덜란드 | F124: 0 | G124: 송이 | H124: 송이
A125: 132 | B125: ANA01-CO0001 | C125: Ananas | D125: 아나나스 | E125: 콜롬비아 | F125: 0
A126: 133 | B126: ANA01-NL0001 | C126: Ananas L Size | D126: 아나나스 | E126: 네덜란드 | F126: 0
A127: 134 | B127: ANA01-NL0002 | C127: Ananas Mini Extra | D127: 아나나스 | E127: 네덜란드 | F127: 0
A128: 135 | B128: ANA01-NL0003 | C128: Ananas Perfecto Brasil 50cm | D128: 아나나스 | E128: 네덜란드 | F128: 0
A129: 136 | B129: ANA01-NL0004 | C129: Ananas Small Extra | D129: 아나나스 | E129: 네덜란드 | F129: 0
A130: 137 | B130: ANA01-NL0005 | C130: Ananas XL Size | D130: 아나나스 | E130: 네덜란드 | F130: 0
A131: 138 | B131: ANE01-NL0001 | C131: Anemone Marianne Panda | D131: 아네모네 | E131: 네덜란드 | F131: 0 | G131: 송이 | H131: 송이
A132: 139 | B132: ANT01-NL0001 | C132: Anthurium Purple | D132: 안시리움 | E132: 네덜란드 | F132: 0 | G132: 송이 | H132: 송이
A133: 140 | B133: ANT01-NL0002 | C133: Anthurium Red | D133: 안시리움 | E133: 네덜란드 | F133: 0 | G133: 송이 | H133: 송이
A134: 141 | B134: ANT01-NL0003 | C134: Anthurium White | D134: 안시리움 | E134: 네덜란드 | F134: 0 | G134: 송이 | H134: 송이
A135: 142 | B135: ANT01-NL0004 | C135: Anthurium Cheers 13cm | D135: 안시리움 | E135: 네덜란드 | F135: 0 | G135: 송이 | H135: 송이
A136: 143 | B136: ANT01-NL0005 | C136: Anthurium Farao | D136: 안시리움 | E136: 네덜란드 | F136: 0 | G136: 송이 | H136: 송이
A137: 144 | B137: ANT01-NL0006 | C137: Anthurium Marysia | D137: 안시리움 | E137: 네덜란드 | F137: 0 | G137: 송이 | H137: 송이
A138: 145 | B138: ANT01-NL0007 | C138: Anthurium Grand Slam | D138: 안시리움 | E138: 네덜란드 | F138: 0 | G138: 송이 | H138: 송이
A139: 146 | B139: ANT01-NL0008 | C139: Anthurium Pink Christina | D139: 안시리움 | E139: 네덜란드 | F139: 0 | G139: 송이 | H139: 송이
A140: 147 | B140: ANT01-NL0009 | C140: Anthurium Safari 13cm | D140: 안시리움 | E140: 네덜란드 | F140: 0 | G140: 송이 | H140: 송이
A141: 148 | B141: ANT01-NL0010 | C141: Anthurium Candy | D141: 안시리움 | E141: 네덜란드 | F141: 0 | G141: 송이 | H141: 송이
A142: 149 | B142: ANT01-NL0011 | C142: Anthurium Holographic | D142: 안시리움 | E142: 네덜란드 | F142: 0 | G142: 송이 | H142: 송이
... A172: 180 | B172: ANT01-NL0063 | C172: Anthurium Gland Slam 11cm | D172: 안시리움 | E172: 네덜란드 | F172: 0 | G172: 송이 | H172: 송이
A173: 181 | B173: ANT01-NL0064 | C173: Anthurium Graciosa 15cm | D173: 안시리움 | E173: 네덜란드 | F173: 0 | G173: 송이 | H173: 송이 | I173: 화이트/
A174: 182 | B174: ANT01-NL0065 | C174: Anthurium Caribo 13cm | D174: 안시리움 | E174: 네덜란드 | F174: 0 | G174: 송이 | H174: 송이
A175: 183 | B175: ANT01-NL0066 | C175: Anthurium Pink Jesolo 13cm | D175: 안시리움 | E175: 네덜란드 | F175: 0 | G175: 송이 | H175: 송이
A176: 184 | B176: ANT01-NL0067 | C176: Anthurium Kaleo 13cm | D176: 안시리움 | E176: 네덜란드 | F176: 0 | G176: 송이 | H176: 송이
A177: 185 | B177: ANT01-NL0068 | C177: Anthurium Lunette 13cm | D177: 안시리움 | E177: 네덜란드 | F177: 0 | G177: 송이 | H177: 송이
A178: 186 | B178: ANT01-NL0069 | C178: Anthurium Sante Royal 11cm | D178: 안시리움 | E178: 네덜란드 | F178: 0 | G178: 송이 | H178: 송이
A179: 187 | B179: ANT01-NL0070 | C179: Anthurium Marea 13cm | D179: 안시리움 | E179: 네덜란드 | F179: 0 | G179: 송이 | H179: 송이
A180: 188 | B180: ANT01-NL0071 | C180: Anthurium Maxima Elegancia 13cm | D180: 안시리움 | E180: 네덜란드 | F180: 0 | G180: 송이 | H180: 송이
A181: 189 | B181: ANT01-NL0072 | C181: Anthurium Calisto 13cm | D181: 안시리움 | E181: 네덜란드 | F181: 0 | G181: 송이 | H181: 송이
...
